[
    {
        "input": "TOYOTA YARIS 1.4D 5P SOL MMT MY11\n1\nOrdine di lavoro\nTCU-23 2539 06.06.2023\nNIKOLA KUZHNINI\nVIA DELLE CALCARE, 23 - 00040 ROCCA DI PAPA\n-\n+39 388 640 4719\nTARGA\nEF358RJ\nKM\n205458\nDETTAGLIO INTERVENTI\nIMPORTO\nIL CLIENTE LAMENTA DISINSERIMENTO DELLE MARCE, CAMBIO PASSA IN NEUTRO DURANTE LA MARCIA,\nNESSUNA SPIA ACCESA\n0,00 \u20ac\nTOTALE NETTO\nIVA\nSCONTO\n0,00 \u20ac\n0,00 \u20ac\n0,00 \u20ac\n0,00\nTOTALE A PAGARE\nIVA INCLUSA \u20ac\nStai - Centro Assistenza Autorizzato\nVia Enrico Ortolani 290 - 00125 Roma\nP.IVA 11741731001\nTelefono 0699335278\ne-mail: info.stai@toyota-italia.it\nhttp://stai-toyota.it/\nORDINE DI LAVORO: TCU-23 2539 del 06.06.2023\nCOPIA CLIENTE - 1 / 3\n",
        "output": "{\"id\": \"TCU-23 2539\", \"total_amount\": 0, \"date\": \"2023-06-06\", \"dealer\": {\"name\": \"Stai - Centro Assistenza Autorizzato\", \"address\": \"Via Enrico Ortolani 290 - 00125 Roma\"}, \"customer\": {\"name\": \"Nikola Kuzhnini\", \"address\": \"VIA DELLE CALCARE, 23 - 00040 ROCCA DI PAPA\", \"email\": null, \"phone_number\": \"+39 388 640 4719\"}, \"car\": {\"model\": \"TOYOTA YARIS 1.4D 5P SOL MMT MY11\", \"plate\": \"EF358RJ\"}}",
        "instruction": "You are a data extraction assistant. Your task is to extract data from the input text and output only a JSON object that strictly follows the schema below:\n\n{\n  \"id\": \"str\",\n  \"total_amount\": \"float\",\n  \"date\": \"str (YYYY-MM-DD)\",\n  \"dealer\": {\n    \"name\": \"str\",\n    \"address\": \"str\"\n  },\n  \"customer\": {\n    \"name\": \"str\",\n    \"address\": \"str\",\n    \"email\": \"str | null\",\n    \"phone_number\": \"str | null\"\n  },\n  \"car\": {\n    \"model\": \"str\",\n    \"plate\": \"str | null\"\n  }\n}\n\nExtraction Rules:\n1. **id**: Extract the value starting with \"TCU\" or \"LCU\" immediately following \"Ordine di lavoro.\" \n2. **total_amount**: Extract the final amount after \"TOTALE COMPLESSIVO IVA INCLUSA.\" \n3. **date**: Extract the date in DD.MM.YYYY format and convert it to YYYY-MM-DD. \n4. **dealer**: Extract the name and address found near \"Telefono\" or \"e-mail.\" \n5. **customer**: Extract the name, address, email, and phone number. If email or phone number is missing, use null. \n6. **car**:\n   - **model**: Extract all lines describing the car starting with the car brand (e.g., \"TOYOTA\").\n   - **plate**: Extract the value found directly below \"TARGA.\"\n\nReturn only a valid JSON object that matches this schema exactly. For any field that is missing or unclear, use null."
    },
    {
        "input": "CONTROLLI ESCLUSIVI TOYOTA\nSCADENZE\nDurante la manutenzione del suo veicolo, il nostro personale spezializzato e\nqualificato proceder\u00e0 con una diagnosi approfondita effettuando i seguenti controlli:\nSicurezza:\nSistema Impianto frenante e freno a\nmano\n\u2022\nAirbag & Cinture di sicurezza\n\u2022\nLuci & Indicatori di direzione\n\u2022\nPressione Pneumatici\n\u2022\nSospensioni & sterzo\n\u2022\nImpianto carburante\n\u2022\nFunzionalit\u00e0:\nFiltro carburante*\n\u2022\nCandele*\n\u2022\nCinghia ausiliari\n\u2022\nSistema Impianto di scarico\n\u2022\nTrasmissione e giunti\n\u2022\nComfort:\nImpianto A/C\n\u2022\nSpazzole tergi Rabbocco liquido lavavetri\n\u2022\nIntrattenimento di bordo\n\u2022\n* se previsto dal piano di manutenzione\nPROSSIMA\n21/09/2022\nMANUTENZIONE\no 110648Km\nSILVIO PICCO\nVia Santa Lucia, 34/d - 12045 Fossano\nTOYOTA AURIS AURIS 1.8H ECVT 5P\nLOUNGE MY14\npicco.silvio@gmail.com\n+39 348 271 0238\nTARGA\nEW 229 ME\nKM\n95.648\nDETTAGLIO INTERVENTI\nIMPORTO\n1 TAGLIANDO AMICO REGULAR HYBRID - TAGLIANDO AMICO REGULAR HYBRID\n319,81 \u20ac\nTOTALE NETTO\nIVA\n319,81 \u20ac\n70,36 \u20ac\nTOTALE SERVICE\nIVA INCLUSA\n390,17 \u20ac\nSCONTO\nIVA INCLUSA\n87,45 \u20ac\nTOTALE A PAGARE\nIVA INCLUSA\n302,72\nRIBAUTO 2\nVia della Morina 4 - 12038 Savigliano\nTelefono 017231191 - Fax 0172711581\nOrdine di lavoro\nTCU-21 001-323   21/09/2021\nPAG. 1/3\n COPIA CLIENTE \nORDINE DI LAVORO: TCU-21 001-323 del 21/09/2021\n",
        "output": "{\"id\": \"TCU-21 001-323\", \"total_amount\": 302.72, \"date\": \"2021-09-21\", \"dealer\": {\"name\": \"RIBAUTO 2\", \"address\": \"Via della Morina 4 - 12038 Savigliano\"}, \"customer\": {\"name\": \"SILVIO PICCO\", \"address\": \"Via Santa Lucia, 34/d - 12045 Fossano\", \"email\": \"picco.silvio@gmail.com\", \"phone_number\": \"+39 348 271 0238\"}, \"car\": {\"model\": \"TOYOTA AURIS AURIS 1.8H ECVT 5P LOUNGE MY14\", \"plate\": \"EW229ME\"}}",
        "instruction": "You are a data extraction assistant. Your task is to extract data from the input text and output only a JSON object that strictly follows the schema below:\n\n{\n  \"id\": \"str\",\n  \"total_amount\": \"float\",\n  \"date\": \"str (YYYY-MM-DD)\",\n  \"dealer\": {\n    \"name\": \"str\",\n    \"address\": \"str\"\n  },\n  \"customer\": {\n    \"name\": \"str\",\n    \"address\": \"str\",\n    \"email\": \"str | null\",\n    \"phone_number\": \"str | null\"\n  },\n  \"car\": {\n    \"model\": \"str\",\n    \"plate\": \"str | null\"\n  }\n}\n\nExtraction Rules:\n1. **id**: Extract the value starting with \"TCU\" or \"LCU\" immediately following \"Ordine di lavoro.\" \n2. **total_amount**: Extract the final amount after \"TOTALE COMPLESSIVO IVA INCLUSA.\" \n3. **date**: Extract the date in DD.MM.YYYY format and convert it to YYYY-MM-DD. \n4. **dealer**: Extract the name and address found near \"Telefono\" or \"e-mail.\" \n5. **customer**: Extract the name, address, email, and phone number. If email or phone number is missing, use null. \n6. **car**:\n   - **model**: Extract all lines describing the car starting with the car brand (e.g., \"TOYOTA\").\n   - **plate**: Extract the value found directly below \"TARGA.\"\n\nReturn only a valid JSON object that matches this schema exactly. For any field that is missing or unclear, use null."
    },
    {
        "input": "CONTROLLI ESCLUSIVI TOYOTA\nSCADENZE\nDurante la manutenzione del suo veicolo, il nostro personale spezializzato e\nqualificato proceder\u00e0 con una diagnosi approfondita effettuando i seguenti\ncontrolli:\nSicurezza:\nSistema Impianto frenante e freno a\nmano\n\u2022\nAirbag & Cinture di sicurezza\n\u2022\nLuci & Indicatori di direzione\n\u2022\nPressione Pneumatici\n\u2022\nSospensioni & sterzo\n\u2022\nImpianto carburante\n\u2022\nFunzionalit\u00e0:\nFiltro carburante*\n\u2022\nCandele*\n\u2022\nCinghia ausiliari\n\u2022\nSistema Impianto di scarico\n\u2022\nTrasmissione e giunti\n\u2022\nComfort:\nImpianto A/C\n\u2022\nSpazzole tergi Rabbocco liquido lavavetri\n\u2022\nIntrattenimento di bordo\n\u2022\n* se previsto dal piano di manutenzione\nPROSSIMA\n09/03/2024\nMANUTENZIONE\no 108735Km\nGIUSEPPA TROVATO MAZZA\nFRAZ. LA FONTAINE - 11020 GRESSAN\nTOYOTA YARIS YARIS 1.5H ECVT 5P\nSTYLE MY17\n+39 335 767 0230\nTARGA\nFH 866 KP\nKM\n93.735\nDETTAGLIO INTERVENTI\nIMPORTO\n1 TAGLIANDO AMICO START\n310,99 \u20ac\nTOTALE NETTO\nIVA\n310,99 \u20ac\n68,42 \u20ac\nTOTALE SERVICE\nIVA INCLUSA\n379,41 \u20ac\nSCONTO\nIVA INCLUSA\n44,91 \u20ac\nTOTALE A PAGARE\nIVA INCLUSA\n334,50\nL'AUTOCENTER\nLocalita Grand Chemin 207 - 11020 Saint Christophe\nTelefono 0165235007 - Fax \nOrdine di lavoro\nTCU-23 001-019   09/03/2023\nPAG. 1/2\n COPIA CLIENTE \nORDINE DI LAVORO: TCU-23 001-019 del 09/03/2023\n",
        "output": "{\"id\": \"TCU-23 001-019\", \"total_amount\": 334.5, \"date\": \"2024-03-09\", \"dealer\": {\"name\": \"L'Autocenter\", \"address\": \"Localita Grand Chemin 207 - 11020 Saint Christophe\"}, \"customer\": {\"name\": \"Giuseppa Trovato Mazz\\u00e0\", \"address\": \"Fraz. La Fontaine - 11020 Gressan\", \"email\": null, \"phone_number\": \"+39 335 767 0230\"}, \"car\": {\"model\": \"Toyota Yaris Yaris 1.5H ECVT 5P Style MY17\", \"plate\": \"FH 866 KP\"}}",
        "instruction": "You are a data extraction assistant. Your task is to extract data from the input text and output only a JSON object that strictly follows the schema below:\n\n{\n  \"id\": \"str\",\n  \"total_amount\": \"float\",\n  \"date\": \"str (YYYY-MM-DD)\",\n  \"dealer\": {\n    \"name\": \"str\",\n    \"address\": \"str\"\n  },\n  \"customer\": {\n    \"name\": \"str\",\n    \"address\": \"str\",\n    \"email\": \"str | null\",\n    \"phone_number\": \"str | null\"\n  },\n  \"car\": {\n    \"model\": \"str\",\n    \"plate\": \"str | null\"\n  }\n}\n\nExtraction Rules:\n1. **id**: Extract the value starting with \"TCU\" or \"LCU\" immediately following \"Ordine di lavoro.\" \n2. **total_amount**: Extract the final amount after \"TOTALE COMPLESSIVO IVA INCLUSA.\" \n3. **date**: Extract the date in DD.MM.YYYY format and convert it to YYYY-MM-DD. \n4. **dealer**: Extract the name and address found near \"Telefono\" or \"e-mail.\" \n5. **customer**: Extract the name, address, email, and phone number. If email or phone number is missing, use null. \n6. **car**:\n   - **model**: Extract all lines describing the car starting with the car brand (e.g., \"TOYOTA\").\n   - **plate**: Extract the value found directly below \"TARGA.\"\n\nReturn only a valid JSON object that matches this schema exactly. For any field that is missing or unclear, use null."
    },
    {
        "input": "CONTROLLI ESCLUSIVI TOYOTA\nSCADENZE\nDurante la manutenzione del suo veicolo, il nostro personale spezializzato e\nqualificato proceder\u00e0 con una diagnosi approfondita effettuando i seguenti\ncontrolli:\nSicurezza:\nSistema Impianto frenante e freno a\nmano\n\u2022\nAirbag & Cinture di sicurezza\n\u2022\nLuci & Indicatori di direzione\n\u2022\nPressione Pneumatici\n\u2022\nSospensioni & sterzo\n\u2022\nImpianto carburante\n\u2022\nFunzionalit\u00e0:\nFiltro carburante*\n\u2022\nCandele*\n\u2022\nCinghia ausiliari\n\u2022\nSistema Impianto di scarico\n\u2022\nTrasmissione e giunti\n\u2022\nComfort:\nImpianto A/C\n\u2022\nSpazzole tergi Rabbocco liquido lavavetri\n\u2022\nIntrattenimento di bordo\n\u2022\n* se previsto dal piano di manutenzione\nPROSSIMA\n13/02/2024\nMANUTENZIONE\no 64531Km\nGIUSEPPE SCARMOZZINO\nVIA NAZIONALE - 89812 PIZZO\nTOYOTA RAV4 RAV4 2.5H ECVT STYL\nAWD-I MY19\nscarmozzino.giuseppe@tiscali.it\n+39 328 719 5184\nTARGA\nFX 112 YY\nKM\n49.531\nDETTAGLIO INTERVENTI\nIMPORTO\n1 TAGLIANDO AMICO START HYBRID - TAGLIANDO AMICO START HYBRID\n322,61 \u20ac\n2 HYBRID BATTERY LOCK - HYBRID BATTERY LOCK\n6,67 \u20ac\n3 CONTROLLO CIGOLIO AVANTRENO\n0,00 \u20ac\n4 COMPLESSIVO RACCHETTA TERGICRISTALLI (ENTRAMBI I LATI), SMONTA E RIMONTA - OPERAZIONE\nBASE\n53,12 \u20ac\nTOTALE NETTO\nIVA\n382,40 \u20ac\n84,13 \u20ac\nTOTALE SERVICE\nIVA INCLUSA\n466,52 \u20ac\nSCONTO\nIVA INCLUSA\n115,60 \u20ac\nTOTALE A PAGARE\nIVA INCLUSA\n350,92\nVADALA'\nS.P.1 Km 2,500 - 89013 Gioia Tauro\nTelefono 0966504341 - Fax 096651543\nhttp://vadala-toyota.it\nOrdine di lavoro\nTCU-23 001-568   13/02/2023\nPAG. 1/3\n COPIA CLIENTE \nORDINE DI LAVORO: TCU-23 001-568 del 13/02/2023\n",
        "output": "{\"id\": \"TCU-23 001-568\", \"total_amount\": 350.92, \"date\": \"2024-02-13\", \"dealer\": {\"name\": \"Vadala'\", \"address\": \"S.P.1 Km 2,500 - 89013 Gioia Tauro\"}, \"customer\": {\"name\": \"Giuseppe Scarmozzino\", \"address\": \"VIA NAZIONALE - 89812 PIZZO\", \"email\": \"scarmozzino.giuseppe@tiscali.it\", \"phone_number\": \"+39 328 719 5184\"}, \"car\": {\"model\": \"Toyota RAV4 RAV4 2.5H ECVT STYL AWD-I MY19\", \"plate\": \"FX 112 YY\"}}",
        "instruction": "You are a data extraction assistant. Your task is to extract data from the input text and output only a JSON object that strictly follows the schema below:\n\n{\n  \"id\": \"str\",\n  \"total_amount\": \"float\",\n  \"date\": \"str (YYYY-MM-DD)\",\n  \"dealer\": {\n    \"name\": \"str\",\n    \"address\": \"str\"\n  },\n  \"customer\": {\n    \"name\": \"str\",\n    \"address\": \"str\",\n    \"email\": \"str | null\",\n    \"phone_number\": \"str | null\"\n  },\n  \"car\": {\n    \"model\": \"str\",\n    \"plate\": \"str | null\"\n  }\n}\n\nExtraction Rules:\n1. **id**: Extract the value starting with \"TCU\" or \"LCU\" immediately following \"Ordine di lavoro.\" \n2. **total_amount**: Extract the final amount after \"TOTALE COMPLESSIVO IVA INCLUSA.\" \n3. **date**: Extract the date in DD.MM.YYYY format and convert it to YYYY-MM-DD. \n4. **dealer**: Extract the name and address found near \"Telefono\" or \"e-mail.\" \n5. **customer**: Extract the name, address, email, and phone number. If email or phone number is missing, use null. \n6. **car**:\n   - **model**: Extract all lines describing the car starting with the car brand (e.g., \"TOYOTA\").\n   - **plate**: Extract the value found directly below \"TARGA.\"\n\nReturn only a valid JSON object that matches this schema exactly. For any field that is missing or unclear, use null."
    },
    {
        "input": "CONTROLLI ESCLUSIVI TOYOTA\nSCADENZE\nDurante la manutenzione del suo veicolo, il nostro personale spezializzato e\nqualificato proceder\u00e0 con una diagnosi approfondita effettuando i seguenti controlli:\nSicurezza:\nSistema Impianto frenante e freno a\nmano\n\u2022\nAirbag & Cinture di sicurezza\n\u2022\nLuci & Indicatori di direzione\n\u2022\nPressione Pneumatici\n\u2022\nSospensioni & sterzo\n\u2022\nImpianto carburante\n\u2022\nFunzionalit\u00e0:\nFiltro carburante*\n\u2022\nCandele*\n\u2022\nCinghia ausiliari\n\u2022\nSistema Impianto di scarico\n\u2022\nTrasmissione e giunti\n\u2022\nComfort:\nImpianto A/C\n\u2022\nSpazzole tergi Rabbocco liquido lavavetri\n\u2022\nIntrattenimento di bordo\n\u2022\n* se previsto dal piano di manutenzione\nPROSSIMA\n21/09/2022\nMANUTENZIONE\no 52006Km\nBARBARA COSTANTINI\nVIA DEL FRANTOIO  - 00060 FORMELLO\nTOYOTA YARIS YARIS 1.5H ECVT 5P\nACTIVE MY18\nBARBARA.COSTANTINI@OUTLOOK.IT\n+39 333 521 8949\nTARGA\nFZ 850 HL\nKM\n37.006\nDETTAGLIO INTERVENTI\nIMPORTO\n1 TAGLIANDO ANNO 2 -30.000KM - OPERAZIONE BASE\n214,50 \u20ac\n2 SOSTITUZIONE FILTRO ARIA MOTORE  - IGIENIZZAZIONE ABITACOLO\n54,84 \u20ac\nTOTALE NETTO\nIVA\n269,34 \u20ac\n59,25 \u20ac\nTOTALE SERVICE\nIVA INCLUSA\n328,59 \u20ac\nSCONTO\nIVA INCLUSA\n31,59 \u20ac\nTOTALE A PAGARE\nIVA INCLUSA\n297,00\nAUTO ROYAL COMPANY\nVia Flaminia, 888 - 00191 Roma\nTelefono 063322881 - Fax 0633228890\nhttp://autoroyalcompany-toyota.it\nOrdine di lavoro\nTCU-21 019-780   21/09/2021\nPAG. 1/3\n COPIA CLIENTE \nORDINE DI LAVORO: TCU-21 019-780 del 21/09/2021\n",
        "output": "{\"id\": \"TCU-21 019-780\", \"total_amount\": 297.0, \"date\": \"2022-09-21\", \"dealer\": {\"name\": \"AUTO ROYAL COMPANY\", \"address\": \"Via Flaminia, 888 - 00191 Roma\"}, \"customer\": {\"name\": \"Barbara Costantini\", \"address\": \"VIA DEL FRANTOIO  - 00060 FORMELLO\", \"email\": \"barbara.costantini@outlook.it\", \"phone_number\": \"+39 333 521 8949\"}, \"car\": {\"model\": \"TOYOTA YARIS YARIS 1.5H ECVT 5P ACTIVE MY18\", \"plate\": \"FZ 850 HL\"}}",
        "instruction": "You are a data extraction assistant. Your task is to extract data from the input text and output only a JSON object that strictly follows the schema below:\n\n{\n  \"id\": \"str\",\n  \"total_amount\": \"float\",\n  \"date\": \"str (YYYY-MM-DD)\",\n  \"dealer\": {\n    \"name\": \"str\",\n    \"address\": \"str\"\n  },\n  \"customer\": {\n    \"name\": \"str\",\n    \"address\": \"str\",\n    \"email\": \"str | null\",\n    \"phone_number\": \"str | null\"\n  },\n  \"car\": {\n    \"model\": \"str\",\n    \"plate\": \"str | null\"\n  }\n}\n\nExtraction Rules:\n1. **id**: Extract the value starting with \"TCU\" or \"LCU\" immediately following \"Ordine di lavoro.\" \n2. **total_amount**: Extract the final amount after \"TOTALE COMPLESSIVO IVA INCLUSA.\" \n3. **date**: Extract the date in DD.MM.YYYY format and convert it to YYYY-MM-DD. \n4. **dealer**: Extract the name and address found near \"Telefono\" or \"e-mail.\" \n5. **customer**: Extract the name, address, email, and phone number. If email or phone number is missing, use null. \n6. **car**:\n   - **model**: Extract all lines describing the car starting with the car brand (e.g., \"TOYOTA\").\n   - **plate**: Extract the value found directly below \"TARGA.\"\n\nReturn only a valid JSON object that matches this schema exactly. For any field that is missing or unclear, use null."
    },
    {
        "input": "CONTROLLI ESCLUSIVI TOYOTA\nSCADENZE\nDurante la manutenzione del suo veicolo, il nostro personale spezializzato e\nqualificato proceder\u00e0 con una diagnosi approfondita effettuando i seguenti controlli:\nSicurezza:\nSistema Impianto frenante e freno a\nmano\n\u2022\nAirbag & Cinture di sicurezza\n\u2022\nLuci & Indicatori di direzione\n\u2022\nPressione Pneumatici\n\u2022\nSospensioni & sterzo\n\u2022\nImpianto carburante\n\u2022\nFunzionalit\u00e0:\nFiltro carburante*\n\u2022\nCandele*\n\u2022\nCinghia ausiliari\n\u2022\nSistema Impianto di scarico\n\u2022\nTrasmissione e giunti\n\u2022\nComfort:\nImpianto A/C\n\u2022\nSpazzole tergi Rabbocco liquido lavavetri\n\u2022\nIntrattenimento di bordo\n\u2022\n* se previsto dal piano di manutenzione\nPROSSIMA\n03/05/2022\nMANUTENZIONE\no 90611Km\nJURI  GIOVANNONE\nVIA CAVOUR  - 22012 CERNOBBIO\nTOYOTA Verso VERSO 1.6B M\nACTIVE MY15\nJURI.GIOVANNONE@LIBERO.IT\n+39 327 464 4190\nTARGA\nFA 224 DA\nKM\n75.611\nDETTAGLIO INTERVENTI\nIMPORTO\n1 TAGLIANDO AMICO REGULAR CONV - TAGLIANDO AMICO REGULAR CONV\n333,94 \u20ac\nTOTALE NETTO\nIVA\n333,94 \u20ac\n73,47 \u20ac\nTOTALE SERVICE\nIVA INCLUSA\n407,41 \u20ac\nSCONTO\nIVA INCLUSA\n96,54 \u20ac\nTOTALE A PAGARE\nIVA INCLUSA\n310,87\nRIVAUTO\nVia Asiago, 28 - 22100 Como\nTelefono 031572270 - Fax 031570631\nhttp://rivauto-toyota.it\nOrdine di lavoro\nTCU-21 006-535   03/05/2021\nPAG. 1/3\n COPIA CLIENTE \nORDINE DI LAVORO: TCU-21 006-535 del 03/05/2021\n",
        "output": "{\"id\": \"TCU-21 006-535\", \"total_amount\": 310.87, \"date\": \"2022-05-03\", \"dealer\": {\"name\": \"Rivauto\", \"address\": \"Via Asiago, 28 - 22100 Como\"}, \"customer\": {\"name\": \"Juri Giovannone\", \"address\": \"VIA CAVOUR  - 22012 CERNOBBIO\", \"email\": \"juri.giovannone@libero.it\", \"phone_number\": \"+39 327 464 4190\"}, \"car\": {\"model\": \"TOYOTA Verso VERSO 1.6B M ACTIVE MY15\", \"plate\": \"FA 224 DA\"}}",
        "instruction": "You are a data extraction assistant. Your task is to extract data from the input text and output only a JSON object that strictly follows the schema below:\n\n{\n  \"id\": \"str\",\n  \"total_amount\": \"float\",\n  \"date\": \"str (YYYY-MM-DD)\",\n  \"dealer\": {\n    \"name\": \"str\",\n    \"address\": \"str\"\n  },\n  \"customer\": {\n    \"name\": \"str\",\n    \"address\": \"str\",\n    \"email\": \"str | null\",\n    \"phone_number\": \"str | null\"\n  },\n  \"car\": {\n    \"model\": \"str\",\n    \"plate\": \"str | null\"\n  }\n}\n\nExtraction Rules:\n1. **id**: Extract the value starting with \"TCU\" or \"LCU\" immediately following \"Ordine di lavoro.\" \n2. **total_amount**: Extract the final amount after \"TOTALE COMPLESSIVO IVA INCLUSA.\" \n3. **date**: Extract the date in DD.MM.YYYY format and convert it to YYYY-MM-DD. \n4. **dealer**: Extract the name and address found near \"Telefono\" or \"e-mail.\" \n5. **customer**: Extract the name, address, email, and phone number. If email or phone number is missing, use null. \n6. **car**:\n   - **model**: Extract all lines describing the car starting with the car brand (e.g., \"TOYOTA\").\n   - **plate**: Extract the value found directly below \"TARGA.\"\n\nReturn only a valid JSON object that matches this schema exactly. For any field that is missing or unclear, use null."
    },
    {
        "input": "Piero Marco Sforza\nVia Manzoni, 142 - 86039 Termoli\nTOYOTA YARIS YARIS 1.5H ECVT 5P\nSTYLE MY15\nSFORZA.MARCO@VIRGILIO.IT\n+39 349 546 7518\nTARGA\nFA 461 XM\nKM\n70.000\nDETTAGLIO INTERVENTI\nIMPORTO\n1 VETTURA GIUNTA CON CARRO SOCCORSO\n46,00 \u20ac\nTOTALE NETTO\nIVA\n46,00 \u20ac\n10,12 \u20ac\nTOTALE A PAGARE\nIVA INCLUSA\n56,12\nPASQUARELLI AUTO\nVia Piane Sant'Angelo 200 - 66050 San Salvo\nTelefono 087334561 - Fax 05844697350\nOrdine di lavoro\nTCU-23 000-942   02/02/2023\nPAG. 1/2\n COPIA CLIENTE \nORDINE DI LAVORO: TCU-23 000-942 del 02/02/2023\n",
        "output": "{\"id\": \"TCU-23 000-942\", \"total_amount\": 56.12, \"date\": \"2023-02-02\", \"dealer\": {\"name\": \"PASQUARELLI AUTO\", \"address\": \"Via Piane Sant'Angelo 200 - 66050 San Salvo\"}, \"customer\": {\"name\": \"Piero Marco Sforza\", \"address\": \"Via Manzoni, 142 - 86039 Termoli\", \"email\": \"sforza.marco@virgilio.it\", \"phone_number\": \"+39 349 546 7518\"}, \"car\": {\"model\": \"TOYOTA YARIS YARIS 1.5H ECVT 5P STYLE MY15\", \"plate\": \"FA 461 XM\"}}",
        "instruction": "You are a data extraction assistant. Your task is to extract data from the input text and output only a JSON object that strictly follows the schema below:\n\n{\n  \"id\": \"str\",\n  \"total_amount\": \"float\",\n  \"date\": \"str (YYYY-MM-DD)\",\n  \"dealer\": {\n    \"name\": \"str\",\n    \"address\": \"str\"\n  },\n  \"customer\": {\n    \"name\": \"str\",\n    \"address\": \"str\",\n    \"email\": \"str | null\",\n    \"phone_number\": \"str | null\"\n  },\n  \"car\": {\n    \"model\": \"str\",\n    \"plate\": \"str | null\"\n  }\n}\n\nExtraction Rules:\n1. **id**: Extract the value starting with \"TCU\" or \"LCU\" immediately following \"Ordine di lavoro.\" \n2. **total_amount**: Extract the final amount after \"TOTALE COMPLESSIVO IVA INCLUSA.\" \n3. **date**: Extract the date in DD.MM.YYYY format and convert it to YYYY-MM-DD. \n4. **dealer**: Extract the name and address found near \"Telefono\" or \"e-mail.\" \n5. **customer**: Extract the name, address, email, and phone number. If email or phone number is missing, use null. \n6. **car**:\n   - **model**: Extract all lines describing the car starting with the car brand (e.g., \"TOYOTA\").\n   - **plate**: Extract the value found directly below \"TARGA.\"\n\nReturn only a valid JSON object that matches this schema exactly. For any field that is missing or unclear, use null."
    },
    {
        "input": "CONTROLLI ESCLUSIVI TOYOTA\nSCADENZE\nDurante la manutenzione del suo veicolo, il nostro personale spezializzato e\nqualificato proceder\u00e0 con una diagnosi approfondita effettuando i seguenti\ncontrolli:\nSicurezza:\nSistema Impianto frenante e freno a\nmano\n\u2022\nAirbag & Cinture di sicurezza\n\u2022\nLuci & Indicatori di direzione\n\u2022\nPressione Pneumatici\n\u2022\nSospensioni & sterzo\n\u2022\nImpianto carburante\n\u2022\nFunzionalit\u00e0:\nFiltro carburante*\n\u2022\nCandele*\n\u2022\nCinghia ausiliari\n\u2022\nSistema Impianto di scarico\n\u2022\nTrasmissione e giunti\n\u2022\nComfort:\nImpianto A/C\n\u2022\nSpazzole tergi Rabbocco liquido lavavetri\n\u2022\nIntrattenimento di bordo\n\u2022\n* se previsto dal piano di manutenzione\nPROSSIMA\n21/02/2024\nMANUTENZIONE\no 16039Km\nDIEGO ANTONECCHIA\nTOYOTA HILUX HILUX 2.4D M DC\n4WD CMF MY21\ndiego.antonecchia@regione.molise.it\n+39 335 128 2812\nTARGA\nGG 418 LM\nKM\n1.039\nDETTAGLIO INTERVENTI\nIMPORTO\n1 ANNO 1 - 15.000 KM - DAT:08/2016\u00b0 + IL CLIENTE CHIEDE DI SISTEMARE IL CAVO A SPIRALE CHE\nFUORIESCE DAL CASSETTO PORTAOGGETTI LATO PASSEGGERO\n0,00 \u20ac\n2 IL CLIENTE SEGNALA IL MANCATO AVVIAMENTO DEL MOTORE ANCHE DOPO UNA BREVE SOSTA E\nCATTIVO ODORE DI ACIDO PROVENIRE DAL VANO MOTORE\n0,00 \u20ac\nTOTALE NETTO\nIVA\n0,00 \u20ac\n0,00 \u20ac\nTOTALE A PAGARE\nIVA INCLUSA\n0,00\nPASQUARELLI AUTO\nC.Da Colle Api V.Giovannitti - 86100 Campabasso\nTelefono 08741863050 - Fax 0874493778\nOrdine di lavoro\nTCU-22 007-573   21/02/2023\nPAG. 1/3\n COPIA CLIENTE \nORDINE DI LAVORO: TCU-22 007-573 del 21/02/2023\n",
        "output": "{\"id\": \"TCU-22 007-573\", \"total_amount\": 0, \"date\": \"2024-02-21\", \"dealer\": {\"name\": \"PASQUARELLI AUTO\", \"address\": \"C.Da Colle Api V.Giovannitti - 86100 Campabasso\"}, \"customer\": {\"name\": \"DIEGO ANTONECCHIA\", \"address\": \"\", \"email\": \"diego.antonecchia@regione.molise.it\", \"phone_number\": \"+39 335 128 2812\"}, \"car\": {\"model\": \"TOYOTA HILUX HILUX 2.4D M DC 4WD CMF MY21\", \"plate\": \"GG 418 LM\"}}",
        "instruction": "You are a data extraction assistant. Your task is to extract data from the input text and output only a JSON object that strictly follows the schema below:\n\n{\n  \"id\": \"str\",\n  \"total_amount\": \"float\",\n  \"date\": \"str (YYYY-MM-DD)\",\n  \"dealer\": {\n    \"name\": \"str\",\n    \"address\": \"str\"\n  },\n  \"customer\": {\n    \"name\": \"str\",\n    \"address\": \"str\",\n    \"email\": \"str | null\",\n    \"phone_number\": \"str | null\"\n  },\n  \"car\": {\n    \"model\": \"str\",\n    \"plate\": \"str | null\"\n  }\n}\n\nExtraction Rules:\n1. **id**: Extract the value starting with \"TCU\" or \"LCU\" immediately following \"Ordine di lavoro.\" \n2. **total_amount**: Extract the final amount after \"TOTALE COMPLESSIVO IVA INCLUSA.\" \n3. **date**: Extract the date in DD.MM.YYYY format and convert it to YYYY-MM-DD. \n4. **dealer**: Extract the name and address found near \"Telefono\" or \"e-mail.\" \n5. **customer**: Extract the name, address, email, and phone number. If email or phone number is missing, use null. \n6. **car**:\n   - **model**: Extract all lines describing the car starting with the car brand (e.g., \"TOYOTA\").\n   - **plate**: Extract the value found directly below \"TARGA.\"\n\nReturn only a valid JSON object that matches this schema exactly. For any field that is missing or unclear, use null."
    },
    {
        "input": "CONTROLLI ESCLUSIVI TOYOTA\nSCADENZE\nDurante la manutenzione del suo veicolo, il nostro personale spezializzato e\nqualificato proceder\u00e0 con una diagnosi approfondita effettuando i seguenti controlli:\nSicurezza:\nSistema Impianto frenante e freno a\nmano\n\u2022\nAirbag & Cinture di sicurezza\n\u2022\nLuci & Indicatori di direzione\n\u2022\nPressione Pneumatici\n\u2022\nSospensioni & sterzo\n\u2022\nImpianto carburante\n\u2022\nFunzionalit\u00e0:\nFiltro carburante*\n\u2022\nCandele*\n\u2022\nCinghia ausiliari\n\u2022\nSistema Impianto di scarico\n\u2022\nTrasmissione e giunti\n\u2022\nComfort:\nImpianto A/C\n\u2022\nSpazzole tergi Rabbocco liquido lavavetri\n\u2022\nIntrattenimento di bordo\n\u2022\n* se previsto dal piano di manutenzione\nPROSSIMA\n21/09/2022\nMANUTENZIONE\no 46518Km\n MASCA PROGETTO BORSA SRL\nVIA GANDHI - 24048 TREVIOLO\nTOYOTA AYGO AYGO 1.0B MMT 5P\nX-CITE MY18\nINFO@MASCAPB.COM\n+39 393 916 1216\nTARGA\nFR 652 YX\nKM\n31.518\nDETTAGLIO INTERVENTI\nIMPORTO\n1 ANNO 3 - 45.000 KM - OPERAZIONE BASE\n220,61 \u20ac\nTOTALE NETTO\nIVA\n220,61 \u20ac\n48,53 \u20ac\nTOTALE SERVICE\nIVA INCLUSA\n269,14 \u20ac\nSCONTO\nIVA INCLUSA\n52,60 \u20ac\nTOTALE A PAGARE\nIVA INCLUSA\n216,54\nSARCO\nVia Bergamo, 15 - 24035 Curno\nTelefono 035460632 - Fax 035463023\nhttp://sarco-toyota.it\nOrdine di lavoro\nTCU-21 013-013   21/09/2021\nPAG. 1/3\n COPIA CLIENTE \nORDINE DI LAVORO: TCU-21 013-013 del 21/09/2021\n",
        "output": "{\"id\": \"TCU-21 013-013\", \"total_amount\": 216.54, \"date\": \"2021-09-21\", \"dealer\": {\"name\": \"SARCO\", \"address\": \"Via Bergamo, 15 - 24035 Curno\"}, \"customer\": {\"name\": \"\", \"address\": \"\", \"email\": null, \"phone_number\": \"+39 393 916 1216\"}, \"car\": {\"model\": \"TOYOTA AYGO AYGO 1.0B MMT 5P X-CITE MY18\", \"plate\": \"FR 652 YX\"}}",
        "instruction": "You are a data extraction assistant. Your task is to extract data from the input text and output only a JSON object that strictly follows the schema below:\n\n{\n  \"id\": \"str\",\n  \"total_amount\": \"float\",\n  \"date\": \"str (YYYY-MM-DD)\",\n  \"dealer\": {\n    \"name\": \"str\",\n    \"address\": \"str\"\n  },\n  \"customer\": {\n    \"name\": \"str\",\n    \"address\": \"str\",\n    \"email\": \"str | null\",\n    \"phone_number\": \"str | null\"\n  },\n  \"car\": {\n    \"model\": \"str\",\n    \"plate\": \"str | null\"\n  }\n}\n\nExtraction Rules:\n1. **id**: Extract the value starting with \"TCU\" or \"LCU\" immediately following \"Ordine di lavoro.\" \n2. **total_amount**: Extract the final amount after \"TOTALE COMPLESSIVO IVA INCLUSA.\" \n3. **date**: Extract the date in DD.MM.YYYY format and convert it to YYYY-MM-DD. \n4. **dealer**: Extract the name and address found near \"Telefono\" or \"e-mail.\" \n5. **customer**: Extract the name, address, email, and phone number. If email or phone number is missing, use null. \n6. **car**:\n   - **model**: Extract all lines describing the car starting with the car brand (e.g., \"TOYOTA\").\n   - **plate**: Extract the value found directly below \"TARGA.\"\n\nReturn only a valid JSON object that matches this schema exactly. For any field that is missing or unclear, use null."
    },
    {
        "input": "GABRIELE FERRERA\nVIA DELLE CAMELIE - 00073 CASTEL GANDOLFO\nTOYOTA YARIS YARIS 15H ECVT 5P\nTREND MY20\nutente0999@gmail.com\n+39 350 165 7277\nTARGA\nGE 119 YL\nKM\n5.051\nDETTAGLIO INTERVENTI\nIMPORTO\n1 SMONTAGGIO E RIMONTAGGIO\n448,40 \u20ac\n2 LATTONERIA\n70,00 \u20ac\n3 VERNICIATURA\n380,00 \u20ac\nTOTALE NETTO\nIVA\n898,40 \u20ac\n197,65 \u20ac\nTOTALE A PAGARE\nIVA INCLUSA\n1.096,05\nA.CORVI\nVia del Lavoro, 2 - 00045 Genzano Di Roma\nTelefono 0693953229 - Fax 069397694\nhttp://acorvi-toyota.it\nOrdine di lavoro\nTCU-21 009-471   21/08/2021\nPAG. 1/3\n COPIA CLIENTE \nORDINE DI LAVORO: TCU-21 009-471 del 21/08/2021\n",
        "output": "{\"id\": \"TCU-21 009-471\", \"total_amount\": 1096.05, \"date\": \"2021-08-21\", \"dealer\": {\"name\": \"A.CORVI\", \"address\": \"Via del Lavoro, 2 - 00045 Genzano Di Roma\"}, \"customer\": {\"name\": \"GABRIELE FERRERA\", \"address\": \"VIA DELLE CAMELIE - 00073 CASTEL GANDOLFO\", \"email\": \"utente0999@gmail.com\", \"phone_number\": \"+39 350 165 7277\"}, \"car\": {\"model\": \"TOYOTA YARIS YARIS 15H ECVT 5P TREND MY20\", \"plate\": \"GE 119 YL\"}}",
        "instruction": "You are a data extraction assistant. Your task is to extract data from the input text and output only a JSON object that strictly follows the schema below:\n\n{\n  \"id\": \"str\",\n  \"total_amount\": \"float\",\n  \"date\": \"str (YYYY-MM-DD)\",\n  \"dealer\": {\n    \"name\": \"str\",\n    \"address\": \"str\"\n  },\n  \"customer\": {\n    \"name\": \"str\",\n    \"address\": \"str\",\n    \"email\": \"str | null\",\n    \"phone_number\": \"str | null\"\n  },\n  \"car\": {\n    \"model\": \"str\",\n    \"plate\": \"str | null\"\n  }\n}\n\nExtraction Rules:\n1. **id**: Extract the value starting with \"TCU\" or \"LCU\" immediately following \"Ordine di lavoro.\" \n2. **total_amount**: Extract the final amount after \"TOTALE COMPLESSIVO IVA INCLUSA.\" \n3. **date**: Extract the date in DD.MM.YYYY format and convert it to YYYY-MM-DD. \n4. **dealer**: Extract the name and address found near \"Telefono\" or \"e-mail.\" \n5. **customer**: Extract the name, address, email, and phone number. If email or phone number is missing, use null. \n6. **car**:\n   - **model**: Extract all lines describing the car starting with the car brand (e.g., \"TOYOTA\").\n   - **plate**: Extract the value found directly below \"TARGA.\"\n\nReturn only a valid JSON object that matches this schema exactly. For any field that is missing or unclear, use null."
    },
    {
        "input": "Toyota Aygo - RC'19 Aygo Hatchback x-\nfun 1.0 VVT-i Automatico 5 marce\n1\nOrdine di lavoro\nTCU-24 8140 02.09.2024\nANTONELLA VECCHIONE\nVIA TIENGO, 19 - 82100 BENEVENTO\nDAMBRA1979@GMAIL.COM\n+39 349 148 5062\nTARGA\nFV169AD\nKM\n22579\nDETTAGLIO INTERVENTI\nIMPORTO\nANNO 5 - 75.000 KM - OPERAZIONE BASE\n182,79 \u20ac\nTOTALE INTERVENTI\nIVA ESCLUSA\n182,79 \u20ac\nIVA\n40,21 \u20ac\nTOTALE INTERVENTI\nIVA INCLUSA\n223,00 \u20ac\nSCONTO\nIVA INCLUSA\n17,03 \u20ac\n205,97\nTOTALE COMPLESSIVO\nIVA INCLUSA \u20ac\nFunari\nVia Antonio Abete, 63 - 82100 Contrada Pezzapiana (BN)\nP.IVA 06906070633\nTelefono 08241400400\ne-mail: onlinereservation@funari-toyota.it\nhttp://funari-toyota.it\nORDINE DI LAVORO: TCU-24 8140 del 02.09.2024\nCOPIA CLIENTE - 1 / 3\n",
        "output": "{\"id\": \"TCU-24 8140\", \"total_amount\": 205.97, \"date\": \"2024-09-02\", \"dealer\": {\"name\": \"Funari\", \"address\": \"Via Antonio Abete, 63 - 82100 Contrada Pezzapiana (BN)\"}, \"customer\": {\"name\": \"Antonella Vecchione\", \"address\": \"VIA TIENGO, 19 - 82100 BENEVENTO\", \"email\": \"dambra1979@gmail.com\", \"phone_number\": \"+39 349 148 5062\"}, \"car\": {\"model\": \"Toyota Aygo - RC'19 Aygo Hatchback x-fun 1.0 VVT-i Automatico 5 marce\", \"plate\": \"FV169AD\"}}",
        "instruction": "You are a data extraction assistant. Your task is to extract data from the input text and output only a JSON object that strictly follows the schema below:\n\n{\n  \"id\": \"str\",\n  \"total_amount\": \"float\",\n  \"date\": \"str (YYYY-MM-DD)\",\n  \"dealer\": {\n    \"name\": \"str\",\n    \"address\": \"str\"\n  },\n  \"customer\": {\n    \"name\": \"str\",\n    \"address\": \"str\",\n    \"email\": \"str | null\",\n    \"phone_number\": \"str | null\"\n  },\n  \"car\": {\n    \"model\": \"str\",\n    \"plate\": \"str | null\"\n  }\n}\n\nExtraction Rules:\n1. **id**: Extract the value starting with \"TCU\" or \"LCU\" immediately following \"Ordine di lavoro.\" \n2. **total_amount**: Extract the final amount after \"TOTALE COMPLESSIVO IVA INCLUSA.\" \n3. **date**: Extract the date in DD.MM.YYYY format and convert it to YYYY-MM-DD. \n4. **dealer**: Extract the name and address found near \"Telefono\" or \"e-mail.\" \n5. **customer**: Extract the name, address, email, and phone number. If email or phone number is missing, use null. \n6. **car**:\n   - **model**: Extract all lines describing the car starting with the car brand (e.g., \"TOYOTA\").\n   - **plate**: Extract the value found directly below \"TARGA.\"\n\nReturn only a valid JSON object that matches this schema exactly. For any field that is missing or unclear, use null."
    },
    {
        "input": " KINTO ITALIA SPA\nVIA KIICIRO TOYODA - 00148 ROMA\nTOYOTA HILUX HILUX 2.4D M DC\n4WD CMF MY21\nkintoitalia@legalmail.it\n+39 06 602301\nTARGA\nGD 213 TN\nKM\n79.397\nDETTAGLIO INTERVENTI\nIMPORTO\n1 IL CLIENTE SEGNALA DI ESSERE RIMASTO IN PANNE , NESSUN ACCOPPIAMENTO AVVIENE\nINSERENDO QUALSIASI MARCIA\n23,00 \u20ac\nTOTALE NETTO\nIVA\n23,00 \u20ac\n5,06 \u20ac\nTOTALE A PAGARE\nIVA INCLUSA\n28,06\nPASQUARELLI AUTO\nC.Da Colle Api V.Giovannitti - 86100 Campabasso\nTelefono 08741863050 - Fax 0874493778\nOrdine di lavoro\nTCU-22 008-135   19/12/2022\nPAG. 1/2\n COPIA CLIENTE \nORDINE DI LAVORO: TCU-22 008-135 del 19/12/2022\n",
        "output": "{\"id\": \"TCU-22 008-135\", \"total_amount\": 28.06, \"date\": \"2022-12-19\", \"dealer\": {\"name\": \"PASQUARELLI AUTO\", \"address\": \"C.Da Colle Api V.Giovannitti - 86100 Campabasso\"}, \"customer\": {\"name\": \"\", \"address\": \"\", \"email\": \"kintoitalia@legalmail.it\", \"phone_number\": \"+39 06 602301\"}, \"car\": {\"model\": \"TOYOTA HILUX HILUX 2.4D M DC 4WD CMF MY21\", \"plate\": \"GD 213 TN\"}}",
        "instruction": "You are a data extraction assistant. Your task is to extract data from the input text and output only a JSON object that strictly follows the schema below:\n\n{\n  \"id\": \"str\",\n  \"total_amount\": \"float\",\n  \"date\": \"str (YYYY-MM-DD)\",\n  \"dealer\": {\n    \"name\": \"str\",\n    \"address\": \"str\"\n  },\n  \"customer\": {\n    \"name\": \"str\",\n    \"address\": \"str\",\n    \"email\": \"str | null\",\n    \"phone_number\": \"str | null\"\n  },\n  \"car\": {\n    \"model\": \"str\",\n    \"plate\": \"str | null\"\n  }\n}\n\nExtraction Rules:\n1. **id**: Extract the value starting with \"TCU\" or \"LCU\" immediately following \"Ordine di lavoro.\" \n2. **total_amount**: Extract the final amount after \"TOTALE COMPLESSIVO IVA INCLUSA.\" \n3. **date**: Extract the date in DD.MM.YYYY format and convert it to YYYY-MM-DD. \n4. **dealer**: Extract the name and address found near \"Telefono\" or \"e-mail.\" \n5. **customer**: Extract the name, address, email, and phone number. If email or phone number is missing, use null. \n6. **car**:\n   - **model**: Extract all lines describing the car starting with the car brand (e.g., \"TOYOTA\").\n   - **plate**: Extract the value found directly below \"TARGA.\"\n\nReturn only a valid JSON object that matches this schema exactly. For any field that is missing or unclear, use null."
    },
    {
        "input": "Carmelo TRIPOLI\nVICOLO PARMENIDE - 90011 BAGHERIA\nTOYOTA C-HR C-HR 1.8H ACTIVE\nMY17\nCARMELO.TRIPOLI@TISCALI.IT\n+39 338 455 6168\nTARGA\nFG 718 RP\nKM\n90.203\nDETTAGLIO INTERVENTI\nIMPORTO\n1 REVISIONE STATALE\n66,61 \u20ac\nTOTALE NETTO\nIVA\n66,61 \u20ac\n12,41 \u20ac\nTOTALE A PAGARE\nIVA INCLUSA\n79,02\nRIOLO MOTORS\nVia Enzo Biagi 8 - 90146 Palermo\nTelefono 091401076 - Fax 0917514810\nhttp://rmotors-toyota.it\nOrdine di lavoro\nTCU-23 000-656   26/01/2023\nPAG. 1/2\n COPIA CLIENTE \nORDINE DI LAVORO: TCU-23 000-656 del 26/01/2023\n",
        "output": "{\"id\": \"TCU-23 000-656\", \"total_amount\": 79.02, \"date\": \"2023-01-26\", \"dealer\": {\"name\": \"Riolo Motors\", \"address\": \"Via Enzo Biagi 8 - 90146 Palermo\"}, \"customer\": {\"name\": \"Carmelo Tripoli\", \"address\": \"Vicolo Parmenide - 90011 Bagheria\", \"email\": \"carmelo.tripoli@tiscali.it\", \"phone_number\": \"+39 338 455 6168\"}, \"car\": {\"model\": \"Toyota C-HR C-HR 1.8H Active MY17\", \"plate\": \"FG718RP\"}}",
        "instruction": "You are a data extraction assistant. Your task is to extract data from the input text and output only a JSON object that strictly follows the schema below:\n\n{\n  \"id\": \"str\",\n  \"total_amount\": \"float\",\n  \"date\": \"str (YYYY-MM-DD)\",\n  \"dealer\": {\n    \"name\": \"str\",\n    \"address\": \"str\"\n  },\n  \"customer\": {\n    \"name\": \"str\",\n    \"address\": \"str\",\n    \"email\": \"str | null\",\n    \"phone_number\": \"str | null\"\n  },\n  \"car\": {\n    \"model\": \"str\",\n    \"plate\": \"str | null\"\n  }\n}\n\nExtraction Rules:\n1. **id**: Extract the value starting with \"TCU\" or \"LCU\" immediately following \"Ordine di lavoro.\" \n2. **total_amount**: Extract the final amount after \"TOTALE COMPLESSIVO IVA INCLUSA.\" \n3. **date**: Extract the date in DD.MM.YYYY format and convert it to YYYY-MM-DD. \n4. **dealer**: Extract the name and address found near \"Telefono\" or \"e-mail.\" \n5. **customer**: Extract the name, address, email, and phone number. If email or phone number is missing, use null. \n6. **car**:\n   - **model**: Extract all lines describing the car starting with the car brand (e.g., \"TOYOTA\").\n   - **plate**: Extract the value found directly below \"TARGA.\"\n\nReturn only a valid JSON object that matches this schema exactly. For any field that is missing or unclear, use null."
    },
    {
        "input": "CONTROLLI ESCLUSIVI TOYOTA\nSCADENZE\nDurante la manutenzione del suo veicolo, il nostro personale spezializzato e\nqualificato proceder\u00e0 con una diagnosi approfondita effettuando i seguenti\ncontrolli:\nSicurezza:\nSistema Impianto frenante e freno a\nmano\n\u2022\nAirbag & Cinture di sicurezza\n\u2022\nLuci & Indicatori di direzione\n\u2022\nPressione Pneumatici\n\u2022\nSospensioni & sterzo\n\u2022\nImpianto carburante\n\u2022\nFunzionalit\u00e0:\nFiltro carburante*\n\u2022\nCandele*\n\u2022\nCinghia ausiliari\n\u2022\nSistema Impianto di scarico\n\u2022\nTrasmissione e giunti\n\u2022\nComfort:\nImpianto A/C\n\u2022\nSpazzole tergi Rabbocco liquido lavavetri\n\u2022\nIntrattenimento di bordo\n\u2022\n* se previsto dal piano di manutenzione\nPROSSIMA\n10/02/2024\nMANUTENZIONE\no 21631Km\nNicola  Fontana\nTOYOTA Yaris Cross YARIS CROSS\n1.5H 2WD TRD MY21\nNicola.1945@yahoo.it\n+39 340 625 3869\nTARGA\nGF 327 DY\nKM\n6.631\nDETTAGLIO INTERVENTI\nIMPORTO\n1 0C4A93: ESEGUIRE ASSISTENZA A 15.000 KM COME DA MANUALE.-OPERAZIONE BASE\n192,99 \u20ac\nTOTALE NETTO\nIVA\n192,99 \u20ac\n42,46 \u20ac\nTOTALE SERVICE\nIVA INCLUSA\n235,45 \u20ac\nSCONTO\nIVA INCLUSA\n35,67 \u20ac\nTOTALE A PAGARE\nIVA INCLUSA\n199,78\nVADALA'\nVia Orso Mario Corbino 34-36 - 98121 Messina\nTelefono 090914651 - Fax 096651543\nhttp://vadala-toyota.it\nOrdine di lavoro\nTCU-23 001-425   10/02/2023\nPAG. 1/2\n COPIA CLIENTE \nORDINE DI LAVORO: TCU-23 001-425 del 10/02/2023\n",
        "output": "{\"id\": \"TCU-23 001-425\", \"total_amount\": 199.78, \"date\": \"2024-02-10\", \"dealer\": {\"name\": \"VADALA'\", \"address\": \"Via Orso Mario Corbino 34-36 - 98121 Messina\"}, \"customer\": {\"name\": \"Nicola Fontana\", \"address\": \"\", \"email\": \"Nicola.1945@yahoo.it\", \"phone_number\": \"+39 340 625 3869\"}, \"car\": {\"model\": \"TOYOTA Yaris Cross YARIS CROSS 1.5H 2WD TRD MY21\", \"plate\": \"GF327DY\"}}",
        "instruction": "You are a data extraction assistant. Your task is to extract data from the input text and output only a JSON object that strictly follows the schema below:\n\n{\n  \"id\": \"str\",\n  \"total_amount\": \"float\",\n  \"date\": \"str (YYYY-MM-DD)\",\n  \"dealer\": {\n    \"name\": \"str\",\n    \"address\": \"str\"\n  },\n  \"customer\": {\n    \"name\": \"str\",\n    \"address\": \"str\",\n    \"email\": \"str | null\",\n    \"phone_number\": \"str | null\"\n  },\n  \"car\": {\n    \"model\": \"str\",\n    \"plate\": \"str | null\"\n  }\n}\n\nExtraction Rules:\n1. **id**: Extract the value starting with \"TCU\" or \"LCU\" immediately following \"Ordine di lavoro.\" \n2. **total_amount**: Extract the final amount after \"TOTALE COMPLESSIVO IVA INCLUSA.\" \n3. **date**: Extract the date in DD.MM.YYYY format and convert it to YYYY-MM-DD. \n4. **dealer**: Extract the name and address found near \"Telefono\" or \"e-mail.\" \n5. **customer**: Extract the name, address, email, and phone number. If email or phone number is missing, use null. \n6. **car**:\n   - **model**: Extract all lines describing the car starting with the car brand (e.g., \"TOYOTA\").\n   - **plate**: Extract the value found directly below \"TARGA.\"\n\nReturn only a valid JSON object that matches this schema exactly. For any field that is missing or unclear, use null."
    },
    {
        "input": "CONTROLLI ESCLUSIVI TOYOTA\nSCADENZE\nDurante la manutenzione del suo veicolo, il nostro personale spezializzato e\nqualificato proceder\u00e0 con una diagnosi approfondita effettuando i seguenti\ncontrolli:\nSicurezza:\nSistema Impianto frenante e freno a\nmano\n\u2022\nAirbag & Cinture di sicurezza\n\u2022\nLuci & Indicatori di direzione\n\u2022\nPressione Pneumatici\n\u2022\nSospensioni & sterzo\n\u2022\nImpianto carburante\n\u2022\nFunzionalit\u00e0:\nFiltro carburante*\n\u2022\nCandele*\n\u2022\nCinghia ausiliari\n\u2022\nSistema Impianto di scarico\n\u2022\nTrasmissione e giunti\n\u2022\nComfort:\nImpianto A/C\n\u2022\nSpazzole tergi Rabbocco liquido lavavetri\n\u2022\nIntrattenimento di bordo\n\u2022\n* se previsto dal piano di manutenzione\nPROSSIMA\n05/10/2021\nMANUTENZIONE\no 174588Km\nMaria Luisa Balestrieri\nVia B. Falcomat\u00e0 44 - 80128 Napoli\nTOYOTA  VERSO 2.0D M 7S ACTIVE\nMY13\nbiagioscogna@gmail.com\n+39 338 597 5043\nTARGA\nER 349 GG\nKM\n159.588\nDETTAGLIO INTERVENTI\nIMPORTO\n1 RIVESTIMENTO DEL PASSARUOTA ANTERIORE (UN LATO), SMONTA E RIMONTA - COMB: OPPOSITE\nSIDE\n307,39 \u20ac\n2 TAGLIANDO AMICO START CONV - TAGLIANDO AMICO START CONV\n209,05 \u20ac\nTOTALE NETTO\nIVA\n516,44 \u20ac\n113,62 \u20ac\nTOTALE SERVICE\nIVA INCLUSA\n630,05 \u20ac\nSCONTO\nIVA INCLUSA\n56,54 \u20ac\nTOTALE A PAGARE\nIVA INCLUSA\n573,51\nDI MAURO\nVia Repubbliche Marinare, 61 - 84131 Napoli\nTelefono 0812286911 - Fax 0812286904\nhttp://dimauro-toyota.it\nOrdine di lavoro\nTCU-20 003-552   05/10/2020\nPAG. 1/3\n COPIA CLIENTE \nORDINE DI LAVORO: TCU-20 003-552 del 05/10/2020\n",
        "output": "{\"id\": \"TCU-20 003-552\", \"total_amount\": 573.51, \"date\": \"2020-10-05\", \"dealer\": {\"name\": \"DI MAURO\", \"address\": \"Via Repubbliche Marinare, 61 - 84131 Napoli\"}, \"customer\": {\"name\": \"Maria Luisa Balestrieri\", \"address\": \"Via B. Falcomat\\u00e0 44 - 80128 Napoli\", \"email\": \"biagioscogna@gmail.com\", \"phone_number\": \"+39 338 597 5043\"}, \"car\": {\"model\": \"TOYOTA VERSO 2.0D M 7S ACTIVE MY13\", \"plate\": \"ER 349 GG\"}}",
        "instruction": "You are a data extraction assistant. Your task is to extract data from the input text and output only a JSON object that strictly follows the schema below:\n\n{\n  \"id\": \"str\",\n  \"total_amount\": \"float\",\n  \"date\": \"str (YYYY-MM-DD)\",\n  \"dealer\": {\n    \"name\": \"str\",\n    \"address\": \"str\"\n  },\n  \"customer\": {\n    \"name\": \"str\",\n    \"address\": \"str\",\n    \"email\": \"str | null\",\n    \"phone_number\": \"str | null\"\n  },\n  \"car\": {\n    \"model\": \"str\",\n    \"plate\": \"str | null\"\n  }\n}\n\nExtraction Rules:\n1. **id**: Extract the value starting with \"TCU\" or \"LCU\" immediately following \"Ordine di lavoro.\" \n2. **total_amount**: Extract the final amount after \"TOTALE COMPLESSIVO IVA INCLUSA.\" \n3. **date**: Extract the date in DD.MM.YYYY format and convert it to YYYY-MM-DD. \n4. **dealer**: Extract the name and address found near \"Telefono\" or \"e-mail.\" \n5. **customer**: Extract the name, address, email, and phone number. If email or phone number is missing, use null. \n6. **car**:\n   - **model**: Extract all lines describing the car starting with the car brand (e.g., \"TOYOTA\").\n   - **plate**: Extract the value found directly below \"TARGA.\"\n\nReturn only a valid JSON object that matches this schema exactly. For any field that is missing or unclear, use null."
    },
    {
        "input": "CONTROLLI ESCLUSIVI TOYOTA\nSCADENZE\nDurante la manutenzione del suo veicolo, il nostro personale spezializzato e\nqualificato proceder\u00e0 con una diagnosi approfondita effettuando i seguenti\ncontrolli:\nSicurezza:\nSistema Impianto frenante e freno a\nmano\n\u2022\nAirbag & Cinture di sicurezza\n\u2022\nLuci & Indicatori di direzione\n\u2022\nPressione Pneumatici\n\u2022\nSospensioni & sterzo\n\u2022\nImpianto carburante\n\u2022\nFunzionalit\u00e0:\nFiltro carburante*\n\u2022\nCandele*\n\u2022\nCinghia ausiliari\n\u2022\nSistema Impianto di scarico\n\u2022\nTrasmissione e giunti\n\u2022\nComfort:\nImpianto A/C\n\u2022\nSpazzole tergi Rabbocco liquido lavavetri\n\u2022\nIntrattenimento di bordo\n\u2022\n* se previsto dal piano di manutenzione\nPROSSIMA\n14/02/2024\nMANUTENZIONE\no 77590Km\nDomenico Parisi\nVIA G. DIVITTORIO - 76011 BISCEGLIE\nTOYOTA AYGO AYGO 10B MMT 5P X-\nCLS BLK MY18\nPIRGNA@LIBERO.IT\n+39 330 433 988\nTARGA\nFT 118 BK\nKM\n62.590\nDETTAGLIO INTERVENTI\nIMPORTO\n1 AMICO START\n174,98 \u20ac\n2 SOST.POLLINE\n39,87 \u20ac\nTOTALE NETTO\nIVA\n214,85 \u20ac\n47,27 \u20ac\nTOTALE SERVICE\nIVA INCLUSA\n262,11 \u20ac\nSCONTO\nIVA INCLUSA\n46,65 \u20ac\nTOTALE A PAGARE\nIVA INCLUSA\n215,46\nDIDIAUTO 2\nVia Trani, 16 - 76121 Barletta\nTelefono 0883532454 - Fax 0883535382\nhttp://didiauto2-toyota.it\nOrdine di lavoro\nTCU-23 000-443   14/02/2023\nPAG. 1/3\n COPIA CLIENTE \nORDINE DI LAVORO: TCU-23 000-443 del 14/02/2023\n",
        "output": "{\"id\": \"TCU-23 000-443\", \"total_amount\": 215.46, \"date\": \"2024-02-14\", \"dealer\": {\"name\": \"DIDIAUTO 2\", \"address\": \"Via Trani, 16 - 76121 Barletta\"}, \"customer\": {\"name\": \"Domenico Parisi\", \"address\": \"VIA G. DIVITTORIO - 76011 BISCEGLIE\", \"email\": \"pirgna@libero.it\", \"phone_number\": \"+39 330 433 988\"}, \"car\": {\"model\": \"TOYOTA AYGO AYGO 10B MMT 5P X-CLS BLK MY18\", \"plate\": \"FT 118 BK\"}}",
        "instruction": "You are a data extraction assistant. Your task is to extract data from the input text and output only a JSON object that strictly follows the schema below:\n\n{\n  \"id\": \"str\",\n  \"total_amount\": \"float\",\n  \"date\": \"str (YYYY-MM-DD)\",\n  \"dealer\": {\n    \"name\": \"str\",\n    \"address\": \"str\"\n  },\n  \"customer\": {\n    \"name\": \"str\",\n    \"address\": \"str\",\n    \"email\": \"str | null\",\n    \"phone_number\": \"str | null\"\n  },\n  \"car\": {\n    \"model\": \"str\",\n    \"plate\": \"str | null\"\n  }\n}\n\nExtraction Rules:\n1. **id**: Extract the value starting with \"TCU\" or \"LCU\" immediately following \"Ordine di lavoro.\" \n2. **total_amount**: Extract the final amount after \"TOTALE COMPLESSIVO IVA INCLUSA.\" \n3. **date**: Extract the date in DD.MM.YYYY format and convert it to YYYY-MM-DD. \n4. **dealer**: Extract the name and address found near \"Telefono\" or \"e-mail.\" \n5. **customer**: Extract the name, address, email, and phone number. If email or phone number is missing, use null. \n6. **car**:\n   - **model**: Extract all lines describing the car starting with the car brand (e.g., \"TOYOTA\").\n   - **plate**: Extract the value found directly below \"TARGA.\"\n\nReturn only a valid JSON object that matches this schema exactly. For any field that is missing or unclear, use null."
    },
    {
        "input": "MICHELE  PARADISO\nPIAZZA GASPARRI 4 - 20161 MILANO\nTOYOTA RAV4 RAV4 2.5H ACTIVE\n2WD MY23\n+39 340 376 0676\nTARGA\n-\nKM\n1\nDETTAGLIO INTERVENTI\nIMPORTO\n1 NAVARRA\n191,71 \u20ac\nTOTALE NETTO\nIVA\n191,71 \u20ac\n42,18 \u20ac\nTOTALE SERVICE\nIVA INCLUSA\n233,89 \u20ac\nSCONTO\nIVA INCLUSA\n45,77 \u20ac\nTOTALE A PAGARE\nIVA INCLUSA\n188,12\nSEF CAR\nVia Pizzoni Alfredo, 14 - 20151 Milano\nTelefono 023927501 - Fax 0233490352\nhttp://sefcar-toyota.it\nOrdine di lavoro\nTDN-23 001-339   20/01/2023\nPAG. 1/2\n COPIA CLIENTE \nORDINE DI LAVORO: TDN-23 001-339 del 20/01/2023\n",
        "output": "{\"id\": \"TDN-23 001-339\", \"total_amount\": 188.12, \"date\": \"2023-01-20\", \"dealer\": {\"name\": \"SEF Car\", \"address\": \"Via Pizzoni Alfredo, 14 - 20151 Milano\"}, \"customer\": {\"name\": \"MICHELE PARADISO\", \"address\": \"PIAZZA GASPARRI 4 - 20161 MILANO\", \"email\": null, \"phone_number\": \"+39 340 376 0676\"}, \"car\": {\"model\": \"TOYOTA RAV4 RAV4 2.5H ACTIVE 2WD MY23\", \"plate\": \"-\"}}",
        "instruction": "You are a data extraction assistant. Your task is to extract data from the input text and output only a JSON object that strictly follows the schema below:\n\n{\n  \"id\": \"str\",\n  \"total_amount\": \"float\",\n  \"date\": \"str (YYYY-MM-DD)\",\n  \"dealer\": {\n    \"name\": \"str\",\n    \"address\": \"str\"\n  },\n  \"customer\": {\n    \"name\": \"str\",\n    \"address\": \"str\",\n    \"email\": \"str | null\",\n    \"phone_number\": \"str | null\"\n  },\n  \"car\": {\n    \"model\": \"str\",\n    \"plate\": \"str | null\"\n  }\n}\n\nExtraction Rules:\n1. **id**: Extract the value starting with \"TCU\" or \"LCU\" immediately following \"Ordine di lavoro.\" \n2. **total_amount**: Extract the final amount after \"TOTALE COMPLESSIVO IVA INCLUSA.\" \n3. **date**: Extract the date in DD.MM.YYYY format and convert it to YYYY-MM-DD. \n4. **dealer**: Extract the name and address found near \"Telefono\" or \"e-mail.\" \n5. **customer**: Extract the name, address, email, and phone number. If email or phone number is missing, use null. \n6. **car**:\n   - **model**: Extract all lines describing the car starting with the car brand (e.g., \"TOYOTA\").\n   - **plate**: Extract the value found directly below \"TARGA.\"\n\nReturn only a valid JSON object that matches this schema exactly. For any field that is missing or unclear, use null."
    },
    {
        "input": "CONTROLLI ESCLUSIVI TOYOTA\nSCADENZE\nDurante la manutenzione del suo veicolo, il nostro personale spezializzato e\nqualificato proceder\u00e0 con una diagnosi approfondita effettuando i seguenti controlli:\nSicurezza:\nSistema Impianto frenante e freno a\nmano\n\u2022\nAirbag & Cinture di sicurezza\n\u2022\nLuci & Indicatori di direzione\n\u2022\nPressione Pneumatici\n\u2022\nSospensioni & sterzo\n\u2022\nImpianto carburante\n\u2022\nFunzionalit\u00e0:\nFiltro carburante*\n\u2022\nCandele*\n\u2022\nCinghia ausiliari\n\u2022\nSistema Impianto di scarico\n\u2022\nTrasmissione e giunti\n\u2022\nComfort:\nImpianto A/C\n\u2022\nSpazzole tergi Rabbocco liquido lavavetri\n\u2022\nIntrattenimento di bordo\n\u2022\n* se previsto dal piano di manutenzione\nPROSSIMA\n21/09/2022\nMANUTENZIONE\no 17747Km\nLUCIANO CAIA\nVIA DEI CILIEGI - 31015 CONEGLIANO\nTOYOTA C-HR C-HR 1.8H TRD MY20\ncaia.luc@virgilio.it\n+39 349 843 9198\nTARGA\nGC 144 PA\nKM\n2.747\nDETTAGLIO INTERVENTI\nIMPORTO\n1 ANNO 1 - 15.000 KM - OPERAZIONE BASE\n192,42 \u20ac\n2 HYBRID BATTERY LOCK - HYBRID BATTERY LOCK\n10,49 \u20ac\nTOTALE NETTO\nIVA\n202,91 \u20ac\n44,64 \u20ac\nTOTALE SERVICE\nIVA INCLUSA\n247,55 \u20ac\nSCONTO\nIVA INCLUSA\n40,11 \u20ac\nTOTALE A PAGARE\nIVA INCLUSA\n207,44\nNORDAUTO\nVia Bradolini, 3 - 31020 San Fior\nTelefono 0438401480 - Fax 0423609912\nhttp://nordauto-toyota.it\nOrdine di lavoro\nTCU-21 017-287   21/09/2021\nPAG. 1/3\n COPIA CLIENTE \nORDINE DI LAVORO: TCU-21 017-287 del 21/09/2021\n",
        "output": "{\"id\": \"TCU-21 017-287\", \"total_amount\": 207.44, \"date\": \"2022-09-21\", \"dealer\": {\"name\": \"NORDAUTO\", \"address\": \"Via Bradolini, 3 - 31020 San Fior\"}, \"customer\": {\"name\": \"LUCIANO CAIA\", \"address\": \"VIA DEI CILIEGI - 31015 CONEGLIANO\", \"email\": \"caia.luc@virgilio.it\", \"phone_number\": \"+39 349 843 9198\"}, \"car\": {\"model\": \"TOYOTA C-HR C-HR 1.8H TRD MY20\", \"plate\": \"GC 144 PA\"}}",
        "instruction": "You are a data extraction assistant. Your task is to extract data from the input text and output only a JSON object that strictly follows the schema below:\n\n{\n  \"id\": \"str\",\n  \"total_amount\": \"float\",\n  \"date\": \"str (YYYY-MM-DD)\",\n  \"dealer\": {\n    \"name\": \"str\",\n    \"address\": \"str\"\n  },\n  \"customer\": {\n    \"name\": \"str\",\n    \"address\": \"str\",\n    \"email\": \"str | null\",\n    \"phone_number\": \"str | null\"\n  },\n  \"car\": {\n    \"model\": \"str\",\n    \"plate\": \"str | null\"\n  }\n}\n\nExtraction Rules:\n1. **id**: Extract the value starting with \"TCU\" or \"LCU\" immediately following \"Ordine di lavoro.\" \n2. **total_amount**: Extract the final amount after \"TOTALE COMPLESSIVO IVA INCLUSA.\" \n3. **date**: Extract the date in DD.MM.YYYY format and convert it to YYYY-MM-DD. \n4. **dealer**: Extract the name and address found near \"Telefono\" or \"e-mail.\" \n5. **customer**: Extract the name, address, email, and phone number. If email or phone number is missing, use null. \n6. **car**:\n   - **model**: Extract all lines describing the car starting with the car brand (e.g., \"TOYOTA\").\n   - **plate**: Extract the value found directly below \"TARGA.\"\n\nReturn only a valid JSON object that matches this schema exactly. For any field that is missing or unclear, use null."
    },
    {
        "input": "VALTER FRACCARO\nVIA CARDANO 79 - 22100 COMO\nTOYOTA AURIS AURIS 1.8H ECVT 5P\nACTIVE MY16\nVALTERFRACCARO18@GMAIL.COM\n+39 338 354 6778\nTARGA\nFF 696 ZL\nKM\n77.627\nDETTAGLIO INTERVENTI\nIMPORTO\n1 AIOI ASSICURAZIONI GESTIONE DANNO KASKO; SIN. NR. 1020YCE21-0.004.721 PERITO DAGLIO\nSIMONE\n1.692,06 \u20ac\nTOTALE NETTO\nIVA\n1.692,06 \u20ac\n372,25 \u20ac\nTOTALE SERVICE\nIVA INCLUSA\n2.064,31 \u20ac\nSCONTO\nIVA INCLUSA\n64,30 \u20ac\nTOTALE A PAGARE\nIVA INCLUSA\n2.000,01\nRIVAUTO\nVia Asiago, 28 - 22100 Como\nTelefono 031572270 - Fax 031570631\nhttp://rivauto-toyota.it\nOrdine di lavoro\nTCU-21 011-175   12/07/2021\nPAG. 1/2\n COPIA CLIENTE \nORDINE DI LAVORO: TCU-21 011-175 del 12/07/2021\n",
        "output": "{\"id\": \"TCU-21 011-175\", \"total_amount\": 2000.01, \"date\": \"2021-07-12\", \"dealer\": {\"name\": \"Rivauto\", \"address\": \"Via Asiago, 28 - 22100 Como\"}, \"customer\": {\"name\": \"Valter Fraccaro\", \"address\": \"VIA CARDANO 79 - 22100 COMO\", \"email\": \"valterfraccaro18@gmail.com\", \"phone_number\": \"+39 338 354 6778\"}, \"car\": {\"model\": \"TOYOTA AURIS AURIS 1.8H ECVT 5P ACTIVE MY16\", \"plate\": \"FF 696 ZL\"}}",
        "instruction": "You are a data extraction assistant. Your task is to extract data from the input text and output only a JSON object that strictly follows the schema below:\n\n{\n  \"id\": \"str\",\n  \"total_amount\": \"float\",\n  \"date\": \"str (YYYY-MM-DD)\",\n  \"dealer\": {\n    \"name\": \"str\",\n    \"address\": \"str\"\n  },\n  \"customer\": {\n    \"name\": \"str\",\n    \"address\": \"str\",\n    \"email\": \"str | null\",\n    \"phone_number\": \"str | null\"\n  },\n  \"car\": {\n    \"model\": \"str\",\n    \"plate\": \"str | null\"\n  }\n}\n\nExtraction Rules:\n1. **id**: Extract the value starting with \"TCU\" or \"LCU\" immediately following \"Ordine di lavoro.\" \n2. **total_amount**: Extract the final amount after \"TOTALE COMPLESSIVO IVA INCLUSA.\" \n3. **date**: Extract the date in DD.MM.YYYY format and convert it to YYYY-MM-DD. \n4. **dealer**: Extract the name and address found near \"Telefono\" or \"e-mail.\" \n5. **customer**: Extract the name, address, email, and phone number. If email or phone number is missing, use null. \n6. **car**:\n   - **model**: Extract all lines describing the car starting with the car brand (e.g., \"TOYOTA\").\n   - **plate**: Extract the value found directly below \"TARGA.\"\n\nReturn only a valid JSON object that matches this schema exactly. For any field that is missing or unclear, use null."
    },
    {
        "input": "Toyota C-HR C-HR SUV Active 1.8 Hybrid\nCambio automatico E-CVT\n1\n2\nOrdine di lavoro\nTCU-24 1097 14.10.2024\nSig. GIUSEPPE CARDILLO\nVIA PIETRO NENNI, 20 - 84030 MONTE SAN GIACOMO\ngiuseppecardillo76@hotmail.it\n+39 338 452 7484\nTARGA\nGE488BN\nKM\n32152\nDETTAGLIO INTERVENTI\nIMPORTO\nSPIA MOTORE\n0,00 \u20ac\nMONTAGGIO PNEUMATICI A DEPOSITO\n48,00 \u20ac\nTOTALE INTERVENTI\nIVA ESCLUSA\n48,00 \u20ac\nIVA\n10,56 \u20ac\nTOTALE INTERVENTI\nIVA INCLUSA\n58,56 \u20ac\nSCONTO\nIVA INCLUSA\n0,00 \u20ac\n58,56\nTOTALE COMPLESSIVO\nIVA INCLUSA \u20ac\nCar One - Centro Assistenza Autorizzato\nVia Santa Maria della Misericordia, 66 - 84036 Sala Consilina\nP.IVA 05646560655\nTelefono 097521466\ne-mail: info.casalmotor@toyota-italia.it\nORDINE DI LAVORO: TCU-24 1097 del 17.10.2024\nCOPIA CLIENTE - 1 / 3\n",
        "output": "{\"id\": \"TCU-24 1097\", \"total_amount\": 58.56, \"date\": \"2024-10-14\", \"dealer\": {\"name\": \"Car One - Centro Assistenza Autorizzato\", \"address\": \"Via Santa Maria della Misericordia, 66 - 84036 Sala Consilina\"}, \"customer\": {\"name\": \"Sig. GIUSEPPE CARDILLO\", \"address\": \"VIA PIETRO NENNI, 20 - 84030 MONTE SAN GIACOMO\", \"email\": \"giuseppecardillo76@hotmail.it\", \"phone_number\": \"+39 338 452 7484\"}, \"car\": {\"model\": \"Toyota C-HR C-HR SUV Active 1.8 Hybrid Cambio automatico E-CVT\", \"plate\": \"GE488BN\"}}",
        "instruction": "You are a data extraction assistant. Your task is to extract data from the input text and output only a JSON object that strictly follows the schema below:\n\n{\n  \"id\": \"str\",\n  \"total_amount\": \"float\",\n  \"date\": \"str (YYYY-MM-DD)\",\n  \"dealer\": {\n    \"name\": \"str\",\n    \"address\": \"str\"\n  },\n  \"customer\": {\n    \"name\": \"str\",\n    \"address\": \"str\",\n    \"email\": \"str | null\",\n    \"phone_number\": \"str | null\"\n  },\n  \"car\": {\n    \"model\": \"str\",\n    \"plate\": \"str | null\"\n  }\n}\n\nExtraction Rules:\n1. **id**: Extract the value starting with \"TCU\" or \"LCU\" immediately following \"Ordine di lavoro.\" \n2. **total_amount**: Extract the final amount after \"TOTALE COMPLESSIVO IVA INCLUSA.\" \n3. **date**: Extract the date in DD.MM.YYYY format and convert it to YYYY-MM-DD. \n4. **dealer**: Extract the name and address found near \"Telefono\" or \"e-mail.\" \n5. **customer**: Extract the name, address, email, and phone number. If email or phone number is missing, use null. \n6. **car**:\n   - **model**: Extract all lines describing the car starting with the car brand (e.g., \"TOYOTA\").\n   - **plate**: Extract the value found directly below \"TARGA.\"\n\nReturn only a valid JSON object that matches this schema exactly. For any field that is missing or unclear, use null."
    },
    {
        "input": "ANNALISA QUARANTA\nVIA BURAGO - 25087 SALO'\nTOYOTA YARIS YARIS 15H ECVT 5P\nTREND G MY17\nquaranta.annalisa@gmail.com\n+39 329 229 4704\nTARGA\nFN 657 BR\nKM\n57.127\nDETTAGLIO INTERVENTI\nIMPORTO\n1 CODIFICA PER SECONDA CHIAVE\n52,00 \u20ac\nTOTALE NETTO\nIVA\n52,00 \u20ac\n11,44 \u20ac\nTOTALE A PAGARE\nIVA INCLUSA\n63,44\nUNIQA BONERA\nVia Mantova snc - 25017 Lonato\nTelefono 0309912669 - Fax 0309912651\nhttp://uniqabonera-toyota.it\nOrdine di lavoro\nTCU-23 004-484   23/05/2023\nPAG. 1/2\n COPIA CLIENTE \nORDINE DI LAVORO: TCU-23 004-484 del 23/05/2023\n",
        "output": "{\"id\": \"TCU-23 004-484\", \"total_amount\": 63.44, \"date\": \"2023-05-23\", \"dealer\": {\"name\": \"UNIQA BONERA\", \"address\": \"Via Mantova snc - 25017 Lonato\"}, \"customer\": {\"name\": \"ANNALISA QUARANTA\", \"address\": \"VIA BURAGO - 25087 SALO'\", \"email\": \"quaranta.annalisa@gmail.com\", \"phone_number\": \"+39 329 229 4704\"}, \"car\": {\"model\": \"TOYOTA YARIS YARIS 15H ECVT 5P TREND G MY17\", \"plate\": \"FN 657 BR\"}}",
        "instruction": "You are a data extraction assistant. Your task is to extract data from the input text and output only a JSON object that strictly follows the schema below:\n\n{\n  \"id\": \"str\",\n  \"total_amount\": \"float\",\n  \"date\": \"str (YYYY-MM-DD)\",\n  \"dealer\": {\n    \"name\": \"str\",\n    \"address\": \"str\"\n  },\n  \"customer\": {\n    \"name\": \"str\",\n    \"address\": \"str\",\n    \"email\": \"str | null\",\n    \"phone_number\": \"str | null\"\n  },\n  \"car\": {\n    \"model\": \"str\",\n    \"plate\": \"str | null\"\n  }\n}\n\nExtraction Rules:\n1. **id**: Extract the value starting with \"TCU\" or \"LCU\" immediately following \"Ordine di lavoro.\" \n2. **total_amount**: Extract the final amount after \"TOTALE COMPLESSIVO IVA INCLUSA.\" \n3. **date**: Extract the date in DD.MM.YYYY format and convert it to YYYY-MM-DD. \n4. **dealer**: Extract the name and address found near \"Telefono\" or \"e-mail.\" \n5. **customer**: Extract the name, address, email, and phone number. If email or phone number is missing, use null. \n6. **car**:\n   - **model**: Extract all lines describing the car starting with the car brand (e.g., \"TOYOTA\").\n   - **plate**: Extract the value found directly below \"TARGA.\"\n\nReturn only a valid JSON object that matches this schema exactly. For any field that is missing or unclear, use null."
    },
    {
        "input": "TOYOTA C-HR C-HR 1.8H TREND MY21\n1\n2\nOrdine di lavoro\nTCU-23 2490 05.06.2023\nIrimiea Danut\nVIA FRANCESCA BERTINI, 6 - 00125 ROMA\ndaniele6.6@libero.it\n+39 348 183 5884\nTARGA\nGF778FM\nKM\n25894\nDETTAGLIO INTERVENTI\nIMPORTO\nANNO 2 - 30.000 KM - OPERAZIONE BASE\n318,67 \u20ac\nRIMUOVERE E SOSTITUIRE L'ELEMENTO FILTRO ARIA (TUTTI).-OPERAZIONE BASE\n25,57 \u20ac\nTOTALE NETTO\nIVA\nSCONTO\n371,68 \u20ac\n81,76 \u20ac\n33,47 \u20ac\n419,97\nTOTALE A PAGARE\nIVA INCLUSA \u20ac\nStai - Centro Assistenza Autorizzato\nVia Enrico Ortolani 290 - 00125 Roma\nP.IVA 11741731001\nTelefono 0699335278\ne-mail: info.stai@toyota-italia.it\nhttp://stai-toyota.it/\nORDINE DI LAVORO: TCU-23 2490 del 05.06.2023\nCOPIA CLIENTE - 1 / 3\n",
        "output": "{\"id\": \"TCU-23 2490\", \"total_amount\": 419.97, \"date\": \"2023-06-05\", \"dealer\": {\"name\": \"Stai - Centro Assistenza Autorizzato\", \"address\": \"Via Enrico Ortolani 290 - 00125 Roma\"}, \"customer\": {\"name\": \"Irimiea Danut\", \"address\": \"VIA FRANCESCA BERTINI, 6 - 00125 ROMA\", \"email\": \"daniele6.6@libero.it\", \"phone_number\": \"+39 348 183 5884\"}, \"car\": {\"model\": \"TOYOTA C-HR C-HR 1.8H TREND MY21\", \"plate\": \"GF778FM\"}}",
        "instruction": "You are a data extraction assistant. Your task is to extract data from the input text and output only a JSON object that strictly follows the schema below:\n\n{\n  \"id\": \"str\",\n  \"total_amount\": \"float\",\n  \"date\": \"str (YYYY-MM-DD)\",\n  \"dealer\": {\n    \"name\": \"str\",\n    \"address\": \"str\"\n  },\n  \"customer\": {\n    \"name\": \"str\",\n    \"address\": \"str\",\n    \"email\": \"str | null\",\n    \"phone_number\": \"str | null\"\n  },\n  \"car\": {\n    \"model\": \"str\",\n    \"plate\": \"str | null\"\n  }\n}\n\nExtraction Rules:\n1. **id**: Extract the value starting with \"TCU\" or \"LCU\" immediately following \"Ordine di lavoro.\" \n2. **total_amount**: Extract the final amount after \"TOTALE COMPLESSIVO IVA INCLUSA.\" \n3. **date**: Extract the date in DD.MM.YYYY format and convert it to YYYY-MM-DD. \n4. **dealer**: Extract the name and address found near \"Telefono\" or \"e-mail.\" \n5. **customer**: Extract the name, address, email, and phone number. If email or phone number is missing, use null. \n6. **car**:\n   - **model**: Extract all lines describing the car starting with the car brand (e.g., \"TOYOTA\").\n   - **plate**: Extract the value found directly below \"TARGA.\"\n\nReturn only a valid JSON object that matches this schema exactly. For any field that is missing or unclear, use null."
    },
    {
        "input": "CONTROLLI ESCLUSIVI TOYOTA\nSCADENZE\nDurante la manutenzione del suo veicolo, il nostro personale spezializzato e\nqualificato proceder\u00e0 con una diagnosi approfondita effettuando i seguenti controlli:\nSicurezza:\nSistema Impianto frenante e freno a\nmano\n\u2022\nAirbag & Cinture di sicurezza\n\u2022\nLuci & Indicatori di direzione\n\u2022\nPressione Pneumatici\n\u2022\nSospensioni & sterzo\n\u2022\nImpianto carburante\n\u2022\nFunzionalit\u00e0:\nFiltro carburante*\n\u2022\nCandele*\n\u2022\nCinghia ausiliari\n\u2022\nSistema Impianto di scarico\n\u2022\nTrasmissione e giunti\n\u2022\nComfort:\nImpianto A/C\n\u2022\nSpazzole tergi Rabbocco liquido lavavetri\n\u2022\nIntrattenimento di bordo\n\u2022\n* se previsto dal piano di manutenzione\nPROSSIMA\n26/08/2022\nMANUTENZIONE\no 20730Km\nmarco restelli\nCAVERZASI - 21050 BESANO\nTOYOTA Corolla COROLLA 1.8H 5P\nSTYLE MY20\nMARCORESTELLI@LIBERO.IT\n+39 346 503 7457\nTARGA\nGA 636 YC\nKM\n5.730\nDETTAGLIO INTERVENTI\nIMPORTO\n1 ANNO 1 - 15.000 KM - OPERAZIONE BASE\n185,46 \u20ac\n2 HYBRID BATTERY LOCK - HYBRID BATTERY LOCK\n13,98 \u20ac\n3 INTERVENTI AGGIUNTIVI CONSIGLIATI\n5,00 \u20ac\nTOTALE NETTO\nIVA\n204,44 \u20ac\n44,98 \u20ac\nTOTALE SERVICE\nIVA INCLUSA\n249,42 \u20ac\nSCONTO\nIVA INCLUSA\n23,16 \u20ac\nTOTALE A PAGARE\nIVA INCLUSA\n226,26\nNOVAUTO\nV.Le Valganna, 61 - 21100 Varese\nTelefono 0332285415 - Fax 0332234814\nhttp://novauto-toyota.it\nOrdine di lavoro\nTCU-21 009-848   26/08/2021\nPAG. 1/3\n COPIA CLIENTE \nORDINE DI LAVORO: TCU-21 009-848 del 26/08/2021\n",
        "output": "{\"id\": \"TCU-21 009-848\", \"total_amount\": 226.26, \"date\": \"2022-08-26\", \"dealer\": {\"name\": \"NOVAUTO\", \"address\": \"V.Le Valganna, 61 - 21100 Varese\"}, \"customer\": {\"name\": \"Marco Restelli\", \"address\": \"CAVERZASI - 21050 BESANO\", \"email\": \"marchorestelli@libero.it\", \"phone_number\": \"+39 346 503 7457\"}, \"car\": {\"model\": \"TOYOTA Corolla COROLLA 1.8H 5P STYLE MY20\", \"plate\": \"GA 636 YC\"}}",
        "instruction": "You are a data extraction assistant. Your task is to extract data from the input text and output only a JSON object that strictly follows the schema below:\n\n{\n  \"id\": \"str\",\n  \"total_amount\": \"float\",\n  \"date\": \"str (YYYY-MM-DD)\",\n  \"dealer\": {\n    \"name\": \"str\",\n    \"address\": \"str\"\n  },\n  \"customer\": {\n    \"name\": \"str\",\n    \"address\": \"str\",\n    \"email\": \"str | null\",\n    \"phone_number\": \"str | null\"\n  },\n  \"car\": {\n    \"model\": \"str\",\n    \"plate\": \"str | null\"\n  }\n}\n\nExtraction Rules:\n1. **id**: Extract the value starting with \"TCU\" or \"LCU\" immediately following \"Ordine di lavoro.\" \n2. **total_amount**: Extract the final amount after \"TOTALE COMPLESSIVO IVA INCLUSA.\" \n3. **date**: Extract the date in DD.MM.YYYY format and convert it to YYYY-MM-DD. \n4. **dealer**: Extract the name and address found near \"Telefono\" or \"e-mail.\" \n5. **customer**: Extract the name, address, email, and phone number. If email or phone number is missing, use null. \n6. **car**:\n   - **model**: Extract all lines describing the car starting with the car brand (e.g., \"TOYOTA\").\n   - **plate**: Extract the value found directly below \"TARGA.\"\n\nReturn only a valid JSON object that matches this schema exactly. For any field that is missing or unclear, use null."
    },
    {
        "input": "CONTROLLI ESCLUSIVI TOYOTA\nSCADENZE\nDurante la manutenzione del suo veicolo, il nostro personale spezializzato e\nqualificato proceder\u00e0 con una diagnosi approfondita effettuando i seguenti controlli:\nSicurezza:\nSistema Impianto frenante e freno a\nmano\n\u2022\nAirbag & Cinture di sicurezza\n\u2022\nLuci & Indicatori di direzione\n\u2022\nPressione Pneumatici\n\u2022\nSospensioni & sterzo\n\u2022\nImpianto carburante\n\u2022\nFunzionalit\u00e0:\nFiltro carburante*\n\u2022\nCandele*\n\u2022\nCinghia ausiliari\n\u2022\nSistema Impianto di scarico\n\u2022\nTrasmissione e giunti\n\u2022\nComfort:\nImpianto A/C\n\u2022\nSpazzole tergi Rabbocco liquido lavavetri\n\u2022\nIntrattenimento di bordo\n\u2022\n* se previsto dal piano di manutenzione\nPROSSIMA\n21/09/2022\nMANUTENZIONE\no 60962Km\nERICA AMA'\nVIA MARCONI 19 - 20091 BRESSO\nTOYOTA YARIS YARIS 1.5H ECVT 5P\nACTIVE MY16\nERICA_AMA@HOTMAIL.COM\n+39 328 437 4489\nTARGA\nFE 764 CW\nKM\n45.962\nDETTAGLIO INTERVENTI\nIMPORTO\n1 ANNO 5 - 75.000 KM - OPERAZIONE BASE\n232,98 \u20ac\n2 VERIFICA DISPLAY RADIO (COMANDI TOUCH OGNI TANTO NON FUNZIONANO)\n0,00 \u20ac\nTOTALE NETTO\nIVA\n232,98 \u20ac\n51,25 \u20ac\nTOTALE SERVICE\nIVA INCLUSA\n284,23 \u20ac\nSCONTO\nIVA INCLUSA\n59,99 \u20ac\nTOTALE A PAGARE\nIVA INCLUSA\n224,24\nSPOTORNO CAR\nViale Fulvio Testi, 6 - 20099 Sesto San Giovanni\nTelefono 0226225087 - Fax 0224412952\nhttp://spotornocar-toyota.it\nOrdine di lavoro\nTCU-21 009-110   21/09/2021\nPAG. 1/3\n COPIA CLIENTE \nORDINE DI LAVORO: TCU-21 009-110 del 21/09/2021\n",
        "output": "{\"id\": \"TCU-21 009-110\", \"total_amount\": 224.24, \"date\": \"2022-09-21\", \"dealer\": {\"name\": \"SPOTORNO CAR\", \"address\": \"Viale Fulvio Testi, 6 - 20099 Sesto San Giovanni\"}, \"customer\": {\"name\": \"ERICA AMA'\", \"address\": \"VIA MARCONI 19 - 20091 BRESSO\", \"email\": \"ERICA_AMA@HOTMAIL.COM\", \"phone_number\": \"+39 328 437 4489\"}, \"car\": {\"model\": \"TOYOTA YARIS YARIS 1.5H ECVT 5P ACTIVE MY16\", \"plate\": \"FE 764 CW\"}}",
        "instruction": "You are a data extraction assistant. Your task is to extract data from the input text and output only a JSON object that strictly follows the schema below:\n\n{\n  \"id\": \"str\",\n  \"total_amount\": \"float\",\n  \"date\": \"str (YYYY-MM-DD)\",\n  \"dealer\": {\n    \"name\": \"str\",\n    \"address\": \"str\"\n  },\n  \"customer\": {\n    \"name\": \"str\",\n    \"address\": \"str\",\n    \"email\": \"str | null\",\n    \"phone_number\": \"str | null\"\n  },\n  \"car\": {\n    \"model\": \"str\",\n    \"plate\": \"str | null\"\n  }\n}\n\nExtraction Rules:\n1. **id**: Extract the value starting with \"TCU\" or \"LCU\" immediately following \"Ordine di lavoro.\" \n2. **total_amount**: Extract the final amount after \"TOTALE COMPLESSIVO IVA INCLUSA.\" \n3. **date**: Extract the date in DD.MM.YYYY format and convert it to YYYY-MM-DD. \n4. **dealer**: Extract the name and address found near \"Telefono\" or \"e-mail.\" \n5. **customer**: Extract the name, address, email, and phone number. If email or phone number is missing, use null. \n6. **car**:\n   - **model**: Extract all lines describing the car starting with the car brand (e.g., \"TOYOTA\").\n   - **plate**: Extract the value found directly below \"TARGA.\"\n\nReturn only a valid JSON object that matches this schema exactly. For any field that is missing or unclear, use null."
    },
    {
        "input": "CONTROLLI ESCLUSIVI TOYOTA\nSCADENZE\nDurante la manutenzione del suo veicolo, il nostro personale spezializzato e\nqualificato proceder\u00e0 con una diagnosi approfondita effettuando i seguenti\ncontrolli:\nSicurezza:\nSistema Impianto frenante e freno a\nmano\n\u2022\nAirbag & Cinture di sicurezza\n\u2022\nLuci & Indicatori di direzione\n\u2022\nPressione Pneumatici\n\u2022\nSospensioni & sterzo\n\u2022\nImpianto carburante\n\u2022\nFunzionalit\u00e0:\nFiltro carburante*\n\u2022\nCandele*\n\u2022\nCinghia ausiliari\n\u2022\nSistema Impianto di scarico\n\u2022\nTrasmissione e giunti\n\u2022\nComfort:\nImpianto A/C\n\u2022\nSpazzole tergi Rabbocco liquido lavavetri\n\u2022\nIntrattenimento di bordo\n\u2022\n* se previsto dal piano di manutenzione\nPROSSIMA\n23/02/2024\nMANUTENZIONE\no 244950Km\nLorenzo Scalise\nVia Astagno 27 - 60100 Ancona\nTOYOTA  PRIUS ACTIVE MY09\nL.SCALISE@UNIVPM.IT\n+39 347 775 8348\nTARGA\nEM 947 RG\nKM\n229.950\nDETTAGLIO INTERVENTI\nIMPORTO\n1 AVARIA SISTEMA ABS\n100,00 \u20ac\n2 TAGLIANDO AMICO REGULAR HYBRID - TAGLIANDO AMICO REGULAR HYBRID\n386,94 \u20ac\nTOTALE NETTO\nIVA\n486,94 \u20ac\n107,12 \u20ac\nTOTALE SERVICE\nIVA INCLUSA\n594,06 \u20ac\nSCONTO\nIVA INCLUSA\n157,71 \u20ac\nTOTALE A PAGARE\nIVA INCLUSA\n436,35\nDAY CAR\nVia Mario Natalucci snc - 60131 Ancona\nTelefono 0712132221 - Fax 0712132229\nOrdine di lavoro\nTCU-23 002-030   23/02/2023\nPAG. 1/3\n COPIA CLIENTE \nORDINE DI LAVORO: TCU-23 002-030 del 23/02/2023\n",
        "output": "{\"id\": \"TCU-23 002-030\", \"total_amount\": 436.35, \"date\": \"2024-02-23\", \"dealer\": {\"name\": \"DAY CAR\", \"address\": \"Via Mario Natalucci snc - 60131 Ancona\"}, \"customer\": {\"name\": \"Lorenzo Scalise\", \"address\": \"Via Astagno 27 - 60100 Ancona\", \"email\": \"l.scalise@univpm.it\", \"phone_number\": \"+39 347 775 8348\"}, \"car\": {\"model\": \"TOYOTA PRIUS ACTIVE MY09\", \"plate\": \"EM 947 RG\"}}",
        "instruction": "You are a data extraction assistant. Your task is to extract data from the input text and output only a JSON object that strictly follows the schema below:\n\n{\n  \"id\": \"str\",\n  \"total_amount\": \"float\",\n  \"date\": \"str (YYYY-MM-DD)\",\n  \"dealer\": {\n    \"name\": \"str\",\n    \"address\": \"str\"\n  },\n  \"customer\": {\n    \"name\": \"str\",\n    \"address\": \"str\",\n    \"email\": \"str | null\",\n    \"phone_number\": \"str | null\"\n  },\n  \"car\": {\n    \"model\": \"str\",\n    \"plate\": \"str | null\"\n  }\n}\n\nExtraction Rules:\n1. **id**: Extract the value starting with \"TCU\" or \"LCU\" immediately following \"Ordine di lavoro.\" \n2. **total_amount**: Extract the final amount after \"TOTALE COMPLESSIVO IVA INCLUSA.\" \n3. **date**: Extract the date in DD.MM.YYYY format and convert it to YYYY-MM-DD. \n4. **dealer**: Extract the name and address found near \"Telefono\" or \"e-mail.\" \n5. **customer**: Extract the name, address, email, and phone number. If email or phone number is missing, use null. \n6. **car**:\n   - **model**: Extract all lines describing the car starting with the car brand (e.g., \"TOYOTA\").\n   - **plate**: Extract the value found directly below \"TARGA.\"\n\nReturn only a valid JSON object that matches this schema exactly. For any field that is missing or unclear, use null."
    },
    {
        "input": "CONTROLLI ESCLUSIVI TOYOTA\nSCADENZE\nDurante la manutenzione del suo veicolo, il nostro personale spezializzato e\nqualificato proceder\u00e0 con una diagnosi approfondita effettuando i seguenti\ncontrolli:\nSicurezza:\nSistema Impianto frenante e freno a\nmano\n\u2022\nAirbag & Cinture di sicurezza\n\u2022\nLuci & Indicatori di direzione\n\u2022\nPressione Pneumatici\n\u2022\nSospensioni & sterzo\n\u2022\nImpianto carburante\n\u2022\nFunzionalit\u00e0:\nFiltro carburante*\n\u2022\nCandele*\n\u2022\nCinghia ausiliari\n\u2022\nSistema Impianto di scarico\n\u2022\nTrasmissione e giunti\n\u2022\nComfort:\nImpianto A/C\n\u2022\nSpazzole tergi Rabbocco liquido lavavetri\n\u2022\nIntrattenimento di bordo\n\u2022\n* se previsto dal piano di manutenzione\nPROSSIMA\n08/05/2024\nMANUTENZIONE\no 63313Km\nDiego Galuppi\nVIALE DELLA GRANDE MURAGLIA - 00144 ROMA\nTOYOTA C-HR C-HR 1.8H TREND\nMY19\nDIEGO.GALUPPI@LIBERO.IT\n+39 338 710 1812\nTARGA\nFW 886 PE\nKM\n48.313\nDETTAGLIO INTERVENTI\nIMPORTO\n1 TAGLIANDO AMICO REGULAR HYBRID - TAGLIANDO AMICO REGULAR HYBRID\n397,11 \u20ac\nTOTALE NETTO\nIVA\n397,11 \u20ac\n87,36 \u20ac\nTOTALE SERVICE\nIVA INCLUSA\n484,47 \u20ac\nSCONTO\nIVA INCLUSA\n132,70 \u20ac\nTOTALE A PAGARE\nIVA INCLUSA\n351,77\nZEROCENTO\nVia Baldovinetti 50 - 00142 Roma\nTelefono 067264161 - Fax 06726416265\nhttp://zerocento-toyota.it\nOrdine di lavoro\nTCU-23 011-024   08/05/2023\nPAG. 1/3\n COPIA CLIENTE \nORDINE DI LAVORO: TCU-23 011-024 del 08/05/2023\n",
        "output": "{\"id\": \"TCU-23 011-024\", \"total_amount\": 351.77, \"date\": \"2024-05-08\", \"dealer\": {\"name\": \"Zerocento\", \"address\": \"Via Baldovinetti 50 - 00142 Roma\"}, \"customer\": {\"name\": \"Diego Galuppi\", \"address\": \"VIALE DELLA GRANDE MURAGLIA - 00144 ROMA\", \"email\": \"diego.galuppi@libero.it\", \"phone_number\": \"+39 338 710 1812\"}, \"car\": {\"model\": \"TOYOTA C-HR C-HR 1.8H TREND MY19\", \"plate\": \"FW 886 PE\"}}",
        "instruction": "You are a data extraction assistant. Your task is to extract data from the input text and output only a JSON object that strictly follows the schema below:\n\n{\n  \"id\": \"str\",\n  \"total_amount\": \"float\",\n  \"date\": \"str (YYYY-MM-DD)\",\n  \"dealer\": {\n    \"name\": \"str\",\n    \"address\": \"str\"\n  },\n  \"customer\": {\n    \"name\": \"str\",\n    \"address\": \"str\",\n    \"email\": \"str | null\",\n    \"phone_number\": \"str | null\"\n  },\n  \"car\": {\n    \"model\": \"str\",\n    \"plate\": \"str | null\"\n  }\n}\n\nExtraction Rules:\n1. **id**: Extract the value starting with \"TCU\" or \"LCU\" immediately following \"Ordine di lavoro.\" \n2. **total_amount**: Extract the final amount after \"TOTALE COMPLESSIVO IVA INCLUSA.\" \n3. **date**: Extract the date in DD.MM.YYYY format and convert it to YYYY-MM-DD. \n4. **dealer**: Extract the name and address found near \"Telefono\" or \"e-mail.\" \n5. **customer**: Extract the name, address, email, and phone number. If email or phone number is missing, use null. \n6. **car**:\n   - **model**: Extract all lines describing the car starting with the car brand (e.g., \"TOYOTA\").\n   - **plate**: Extract the value found directly below \"TARGA.\"\n\nReturn only a valid JSON object that matches this schema exactly. For any field that is missing or unclear, use null."
    },
    {
        "input": "TOYOTA YARIS YARIS 15H ECVT 5P\nY20BIT MY18+\n1\nOrdine di lavoro\nTCU-24 19106 18.10.2024\nMaria Luisa Rota\nVIA GIOVANNI BATTISTA RAMPINELLI, 6D - 24126 BERGAMO\ntelmarota@gmail.com\n+39 339 332 5462\nTARGA\nFX830LN\nKM\n60616\nDETTAGLIO INTERVENTI\nIMPORTO\nCAMBIO GOMME (CLIENTE)\n68,40 \u20ac\nTOTALE INTERVENTI\nIVA ESCLUSA\n68,40 \u20ac\nIVA\n15,05 \u20ac\nTOTALE INTERVENTI\nIVA INCLUSA\n83,45 \u20ac\nSCONTO\nIVA INCLUSA\n37,55 \u20ac\n45,90\nTOTALE COMPLESSIVO\nIVA INCLUSA \u20ac\nSarco\nVia Bergamo, 15 - 24035 Curno\nP.IVA 01955130164\nTelefono 035460632\ne-mail: info.sarco@toyota-italia.it\nhttp://sarco-toyota.it\nORDINE DI LAVORO: TCU-24 19106 del 18.10.2024\nCOPIA CLIENTE - 1 / 3\n",
        "output": "{\"id\": \"TCU-24 19106\", \"total_amount\": 45.9, \"date\": \"2024-10-18\", \"dealer\": {\"name\": \"Sarco\", \"address\": \"Via Bergamo, 15 - 24035 Curno\"}, \"customer\": {\"name\": \"Maria Luisa Rota\", \"address\": \"VIA GIOVANNI BATTISTA RAMPINELLI, 6D - 24126 BERGAMO\", \"email\": \"telmarota@gmail.com\", \"phone_number\": \"+39 339 332 5462\"}, \"car\": {\"model\": \"TOYOTA YARIS YARIS 15H ECVT 5P Y20BIT MY18+\", \"plate\": \"FX830LN\"}}",
        "instruction": "You are a data extraction assistant. Your task is to extract data from the input text and output only a JSON object that strictly follows the schema below:\n\n{\n  \"id\": \"str\",\n  \"total_amount\": \"float\",\n  \"date\": \"str (YYYY-MM-DD)\",\n  \"dealer\": {\n    \"name\": \"str\",\n    \"address\": \"str\"\n  },\n  \"customer\": {\n    \"name\": \"str\",\n    \"address\": \"str\",\n    \"email\": \"str | null\",\n    \"phone_number\": \"str | null\"\n  },\n  \"car\": {\n    \"model\": \"str\",\n    \"plate\": \"str | null\"\n  }\n}\n\nExtraction Rules:\n1. **id**: Extract the value starting with \"TCU\" or \"LCU\" immediately following \"Ordine di lavoro.\" \n2. **total_amount**: Extract the final amount after \"TOTALE COMPLESSIVO IVA INCLUSA.\" \n3. **date**: Extract the date in DD.MM.YYYY format and convert it to YYYY-MM-DD. \n4. **dealer**: Extract the name and address found near \"Telefono\" or \"e-mail.\" \n5. **customer**: Extract the name, address, email, and phone number. If email or phone number is missing, use null. \n6. **car**:\n   - **model**: Extract all lines describing the car starting with the car brand (e.g., \"TOYOTA\").\n   - **plate**: Extract the value found directly below \"TARGA.\"\n\nReturn only a valid JSON object that matches this schema exactly. For any field that is missing or unclear, use null."
    },
    {
        "input": "TOYOTA C-HR C-HR 2.0H TREND MY21\n1\n2\n3\nOrdine di lavoro\nTCU-23 2561 06.06.2023\nKarim Fraboni\nVia Agostino Roscelli 6, SNC - 00125 Roma\nKWOP82@YAHOO.IT\n+39 06 5231 1362\nTARGA\nGF368WH\nKM\n29086\nDETTAGLIO INTERVENTI\nIMPORTO\nANNO 2 - 30.000 KM - DAT:\u00b011/2021\n321,28 \u20ac\nEFFETTUARE IL CAMBIO DI POSIZIONE PNEUMATICI.-ASSISTENZA PRINCIPALE\n0,00 \u20ac\nRIMUOVERE E SOSTITUIRE L'ELEMENTO FILTRO ARIA (TUTTI).-OPERAZIONE BASE\n40,44 \u20ac\nTOTALE NETTO\nIVA\nSCONTO\n389,16 \u20ac\n85,60 \u20ac\n33,47 \u20ac\n441,29\nTOTALE A PAGARE\nIVA INCLUSA \u20ac\nStai - Centro Assistenza Autorizzato\nVia Enrico Ortolani 290 - 00125 Roma\nP.IVA 11741731001\nTelefono 0699335278\ne-mail: info.stai@toyota-italia.it\nhttp://stai-toyota.it/\nORDINE DI LAVORO: TCU-23 2561 del 06.06.2023\nCOPIA CLIENTE - 1 / 3\n",
        "output": "{\"id\": \"TCU-23 2561\", \"total_amount\": 441.29, \"date\": \"2023-06-06\", \"dealer\": {\"name\": \"Stai - Centro Assistenza Autorizzato\", \"address\": \"Via Enrico Ortolani 290 - 00125 Roma\"}, \"customer\": {\"name\": \"Karim Fraboni\", \"address\": \"Via Agostino Roscelli 6, SNC - 00125 Roma\", \"email\": \"kwop82@yahoo.it\", \"phone_number\": \"+39 06 5231 1362\"}, \"car\": {\"model\": \"TOYOTA C-HR C-HR 2.0H TREND MY21\", \"plate\": \"GF368WH\"}}",
        "instruction": "You are a data extraction assistant. Your task is to extract data from the input text and output only a JSON object that strictly follows the schema below:\n\n{\n  \"id\": \"str\",\n  \"total_amount\": \"float\",\n  \"date\": \"str (YYYY-MM-DD)\",\n  \"dealer\": {\n    \"name\": \"str\",\n    \"address\": \"str\"\n  },\n  \"customer\": {\n    \"name\": \"str\",\n    \"address\": \"str\",\n    \"email\": \"str | null\",\n    \"phone_number\": \"str | null\"\n  },\n  \"car\": {\n    \"model\": \"str\",\n    \"plate\": \"str | null\"\n  }\n}\n\nExtraction Rules:\n1. **id**: Extract the value starting with \"TCU\" or \"LCU\" immediately following \"Ordine di lavoro.\" \n2. **total_amount**: Extract the final amount after \"TOTALE COMPLESSIVO IVA INCLUSA.\" \n3. **date**: Extract the date in DD.MM.YYYY format and convert it to YYYY-MM-DD. \n4. **dealer**: Extract the name and address found near \"Telefono\" or \"e-mail.\" \n5. **customer**: Extract the name, address, email, and phone number. If email or phone number is missing, use null. \n6. **car**:\n   - **model**: Extract all lines describing the car starting with the car brand (e.g., \"TOYOTA\").\n   - **plate**: Extract the value found directly below \"TARGA.\"\n\nReturn only a valid JSON object that matches this schema exactly. For any field that is missing or unclear, use null."
    },
    {
        "input": "CONTROLLI ESCLUSIVI TOYOTA\nSCADENZE\nDurante la manutenzione del suo veicolo, il nostro personale spezializzato e\nqualificato proceder\u00e0 con una diagnosi approfondita effettuando i seguenti controlli:\nSicurezza:\nSistema Impianto frenante e freno a\nmano\n\u2022\nAirbag & Cinture di sicurezza\n\u2022\nLuci & Indicatori di direzione\n\u2022\nPressione Pneumatici\n\u2022\nSospensioni & sterzo\n\u2022\nImpianto carburante\n\u2022\nFunzionalit\u00e0:\nFiltro carburante*\n\u2022\nCandele*\n\u2022\nCinghia ausiliari\n\u2022\nSistema Impianto di scarico\n\u2022\nTrasmissione e giunti\n\u2022\nComfort:\nImpianto A/C\n\u2022\nSpazzole tergi Rabbocco liquido lavavetri\n\u2022\nIntrattenimento di bordo\n\u2022\n* se previsto dal piano di manutenzione\nPROSSIMA\n19/03/2020\nMANUTENZIONE\no 30932Km\ndario pergolotti\nTOYOTA RAV4 RAV4 25H ECVT\nDYNAMIC+2WD MY18\ndario.pergolotti@toyota-europe.com\n+39 335 675 6873\nTARGA\nFR 371 VV\nKM\n15.932\nDETTAGLIO INTERVENTI\nIMPORTO\n1 TAGLIANDO 1 - 15.000 KM - OPERAZIONE BASE\n234,29 \u20ac\nTOTALE NETTO\nIVA\n234,29 \u20ac\n51,54 \u20ac\nTOTALE SERVICE\nIVA INCLUSA\n285,83 \u20ac\nSCONTO\nIVA INCLUSA\n72,22 \u20ac\nTOTALE A PAGARE\nIVA INCLUSA\n213,61\nA.CORVI\nVia del Lavoro, 2 - 00045 Genzano Di Roma\nTelefono 0693953229 - Fax 069397694\nhttp://acorvi-toyota.it\nOrdine di lavoro\nTCU-19 003-695   19/03/2019\nPAG. 1/2\n COPIA CLIENTE \nORDINE DI LAVORO: TCU-19 003-695 del 19/03/2019\n",
        "output": "{\"id\": \"TCU-19 003-695\", \"total_amount\": 213.61, \"date\": \"2020-03-19\", \"dealer\": {\"name\": \"A.CORVI\", \"address\": \"Via del Lavoro, 2 - 00045 Genzano Di Roma\"}, \"customer\": {\"name\": \"Dario Pergolotti\", \"address\": \"\", \"email\": \"dario.pergolotti@toyota-europe.com\", \"phone_number\": \"+39 335 675 6873\"}, \"car\": {\"model\": \"TOYOTA RAV4 RAV4 25H ECVT DYNAMIC+2WD MY18\", \"plate\": \"FR 371 VV\"}}",
        "instruction": "You are a data extraction assistant. Your task is to extract data from the input text and output only a JSON object that strictly follows the schema below:\n\n{\n  \"id\": \"str\",\n  \"total_amount\": \"float\",\n  \"date\": \"str (YYYY-MM-DD)\",\n  \"dealer\": {\n    \"name\": \"str\",\n    \"address\": \"str\"\n  },\n  \"customer\": {\n    \"name\": \"str\",\n    \"address\": \"str\",\n    \"email\": \"str | null\",\n    \"phone_number\": \"str | null\"\n  },\n  \"car\": {\n    \"model\": \"str\",\n    \"plate\": \"str | null\"\n  }\n}\n\nExtraction Rules:\n1. **id**: Extract the value starting with \"TCU\" or \"LCU\" immediately following \"Ordine di lavoro.\" \n2. **total_amount**: Extract the final amount after \"TOTALE COMPLESSIVO IVA INCLUSA.\" \n3. **date**: Extract the date in DD.MM.YYYY format and convert it to YYYY-MM-DD. \n4. **dealer**: Extract the name and address found near \"Telefono\" or \"e-mail.\" \n5. **customer**: Extract the name, address, email, and phone number. If email or phone number is missing, use null. \n6. **car**:\n   - **model**: Extract all lines describing the car starting with the car brand (e.g., \"TOYOTA\").\n   - **plate**: Extract the value found directly below \"TARGA.\"\n\nReturn only a valid JSON object that matches this schema exactly. For any field that is missing or unclear, use null."
    },
    {
        "input": "CONTROLLI ESCLUSIVI TOYOTA\nSCADENZE\nDurante la manutenzione del suo veicolo, il nostro personale spezializzato e\nqualificato proceder\u00e0 con una diagnosi approfondita effettuando i seguenti\ncontrolli:\nSicurezza:\nSistema Impianto frenante e freno a\nmano\n\u2022\nAirbag & Cinture di sicurezza\n\u2022\nLuci & Indicatori di direzione\n\u2022\nPressione Pneumatici\n\u2022\nSospensioni & sterzo\n\u2022\nImpianto carburante\n\u2022\nFunzionalit\u00e0:\nFiltro carburante*\n\u2022\nCandele*\n\u2022\nCinghia ausiliari\n\u2022\nSistema Impianto di scarico\n\u2022\nTrasmissione e giunti\n\u2022\nComfort:\nImpianto A/C\n\u2022\nSpazzole tergi Rabbocco liquido lavavetri\n\u2022\nIntrattenimento di bordo\n\u2022\n* se previsto dal piano di manutenzione\nPROSSIMA\n28/04/2024\nMANUTENZIONE\no 104134Km\nViviana De Leonardis\nVia Cagliari, 6 - 87064 Montalto Uffugo\nTOYOTA  YARIS 1.0 5P MT MY09\nvivianadeleonardis@gmail.com\n+39 340 654 8147\nTARGA\nDZ 585 LP\nKM\n89.134\nDETTAGLIO INTERVENTI\nIMPORTO\n1 TAGLIANDO AMICO FULL 10+ CONV - TAGLIANDO AMICO FULL 10+ CONV\n263,57 \u20ac\nTOTALE NETTO\nIVA\n263,57 \u20ac\n57,99 \u20ac\nTOTALE SERVICE\nIVA INCLUSA\n321,55 \u20ac\nSCONTO\nIVA INCLUSA\n121,55 \u20ac\nTOTALE A PAGARE\nIVA INCLUSA\n200,00\nCHIAPPETTA AUTO\nVia Umberto Nobile 84 - 87036 Rende\nTelefono 09841758169 - Fax \nOrdine di lavoro\nTCU-23 001-370   28/04/2023\nPAG. 1/3\n COPIA CLIENTE \nORDINE DI LAVORO: TCU-23 001-370 del 28/04/2023\n",
        "output": "{\"id\": \"TCU-23 001-370\", \"total_amount\": 200, \"date\": \"2023-04-28\", \"dealer\": {\"name\": \"CHIAPPETTA AUTO\", \"address\": \"Via Umberto Nobile 84 - 87036 Rende\"}, \"customer\": {\"name\": \"Viviana De Leonardis\", \"address\": \"Via Cagliari, 6 - 87064 Montalto Uffugo\", \"email\": \"vivianadeleonardis@gmail.com\", \"phone_number\": \"+39 340 654 8147\"}, \"car\": {\"model\": \"TOYOTA YARIS 1.0 5P MT MY09\", \"plate\": \"DZ 585 LP\"}}",
        "instruction": "You are a data extraction assistant. Your task is to extract data from the input text and output only a JSON object that strictly follows the schema below:\n\n{\n  \"id\": \"str\",\n  \"total_amount\": \"float\",\n  \"date\": \"str (YYYY-MM-DD)\",\n  \"dealer\": {\n    \"name\": \"str\",\n    \"address\": \"str\"\n  },\n  \"customer\": {\n    \"name\": \"str\",\n    \"address\": \"str\",\n    \"email\": \"str | null\",\n    \"phone_number\": \"str | null\"\n  },\n  \"car\": {\n    \"model\": \"str\",\n    \"plate\": \"str | null\"\n  }\n}\n\nExtraction Rules:\n1. **id**: Extract the value starting with \"TCU\" or \"LCU\" immediately following \"Ordine di lavoro.\" \n2. **total_amount**: Extract the final amount after \"TOTALE COMPLESSIVO IVA INCLUSA.\" \n3. **date**: Extract the date in DD.MM.YYYY format and convert it to YYYY-MM-DD. \n4. **dealer**: Extract the name and address found near \"Telefono\" or \"e-mail.\" \n5. **customer**: Extract the name, address, email, and phone number. If email or phone number is missing, use null. \n6. **car**:\n   - **model**: Extract all lines describing the car starting with the car brand (e.g., \"TOYOTA\").\n   - **plate**: Extract the value found directly below \"TARGA.\"\n\nReturn only a valid JSON object that matches this schema exactly. For any field that is missing or unclear, use null."
    },
    {
        "input": "CONTROLLI ESCLUSIVI TOYOTA\nSCADENZE\nDurante la manutenzione del suo veicolo, il nostro personale spezializzato e\nqualificato proceder\u00e0 con una diagnosi approfondita effettuando i seguenti\ncontrolli:\nSicurezza:\nSistema Impianto frenante e freno a\nmano\n\u2022\nAirbag & Cinture di sicurezza\n\u2022\nLuci & Indicatori di direzione\n\u2022\nPressione Pneumatici\n\u2022\nSospensioni & sterzo\n\u2022\nImpianto carburante\n\u2022\nFunzionalit\u00e0:\nFiltro carburante*\n\u2022\nCandele*\n\u2022\nCinghia ausiliari\n\u2022\nSistema Impianto di scarico\n\u2022\nTrasmissione e giunti\n\u2022\nComfort:\nImpianto A/C\n\u2022\nSpazzole tergi Rabbocco liquido lavavetri\n\u2022\nIntrattenimento di bordo\n\u2022\n* se previsto dal piano di manutenzione\nPROSSIMA\n26/01/2024\nMANUTENZIONE\no 34987Km\nROBERTO TOZZO\nVIA MONTI - 21059 VIGGIU'\nTOYOTA PROACE PROACE 1.5D120M\nL0 S CMF MY21\n+39 338 802 6299\nTARGA\n-\nKM\n19.987\nDETTAGLIO INTERVENTI\nIMPORTO\n1 ESEGUIRE L'ASSISTENZA A 40.000 KM (25.000 MIGLIA)/2 ANNI - OPERAZIONE BASE\n369,60 \u20ac\n2 INTERVENTI AGGIUNTIVI CONSIGLIATI\n54,96 \u20ac\nTOTALE NETTO\nIVA\n424,56 \u20ac\n93,41 \u20ac\nTOTALE SERVICE\nIVA INCLUSA\n517,97 \u20ac\nSCONTO\nIVA INCLUSA\n13,96 \u20ac\nTOTALE A PAGARE\nIVA INCLUSA\n504,01\nNOVAUTO\nV.Le Valganna, 61 - 21100 Varese\nTelefono 0332285415 - Fax 0332234814\nhttp://novauto-toyota.it\nOrdine di lavoro\nTCU-23 001-106   26/01/2023\nPAG. 1/3\n COPIA CLIENTE \nORDINE DI LAVORO: TCU-23 001-106 del 26/01/2023\n",
        "output": "{\"id\": \"TCU-23 001-106\", \"total_amount\": 504.01, \"date\": \"2024-01-26\", \"dealer\": {\"name\": \"NOVAUTO\", \"address\": \"V.Le Valganna, 61 - 21100 Varese\"}, \"customer\": {\"name\": \"ROBERTO TOZZO\", \"address\": \"VIA MONTI - 21059 VIGGIU'\", \"email\": null, \"phone_number\": \"+39 338 802 6299\"}, \"car\": {\"model\": \"TOYOTA PROACE PROACE 1.5D120M L0 S CMF MY21\", \"plate\": null}}",
        "instruction": "You are a data extraction assistant. Your task is to extract data from the input text and output only a JSON object that strictly follows the schema below:\n\n{\n  \"id\": \"str\",\n  \"total_amount\": \"float\",\n  \"date\": \"str (YYYY-MM-DD)\",\n  \"dealer\": {\n    \"name\": \"str\",\n    \"address\": \"str\"\n  },\n  \"customer\": {\n    \"name\": \"str\",\n    \"address\": \"str\",\n    \"email\": \"str | null\",\n    \"phone_number\": \"str | null\"\n  },\n  \"car\": {\n    \"model\": \"str\",\n    \"plate\": \"str | null\"\n  }\n}\n\nExtraction Rules:\n1. **id**: Extract the value starting with \"TCU\" or \"LCU\" immediately following \"Ordine di lavoro.\" \n2. **total_amount**: Extract the final amount after \"TOTALE COMPLESSIVO IVA INCLUSA.\" \n3. **date**: Extract the date in DD.MM.YYYY format and convert it to YYYY-MM-DD. \n4. **dealer**: Extract the name and address found near \"Telefono\" or \"e-mail.\" \n5. **customer**: Extract the name, address, email, and phone number. If email or phone number is missing, use null. \n6. **car**:\n   - **model**: Extract all lines describing the car starting with the car brand (e.g., \"TOYOTA\").\n   - **plate**: Extract the value found directly below \"TARGA.\"\n\nReturn only a valid JSON object that matches this schema exactly. For any field that is missing or unclear, use null."
    },
    {
        "input": "CONTROLLI ESCLUSIVI TOYOTA\nSCADENZE\nDurante la manutenzione del suo veicolo, il nostro personale spezializzato e\nqualificato proceder\u00e0 con una diagnosi approfondita effettuando i seguenti\ncontrolli:\nSicurezza:\nSistema Impianto frenante e freno a\nmano\n\u2022\nAirbag & Cinture di sicurezza\n\u2022\nLuci & Indicatori di direzione\n\u2022\nPressione Pneumatici\n\u2022\nSospensioni & sterzo\n\u2022\nImpianto carburante\n\u2022\nFunzionalit\u00e0:\nFiltro carburante*\n\u2022\nCandele*\n\u2022\nCinghia ausiliari\n\u2022\nSistema Impianto di scarico\n\u2022\nTrasmissione e giunti\n\u2022\nComfort:\nImpianto A/C\n\u2022\nSpazzole tergi Rabbocco liquido lavavetri\n\u2022\nIntrattenimento di bordo\n\u2022\n* se previsto dal piano di manutenzione\nPROSSIMA\n09/03/2024\nMANUTENZIONE\no 108735Km\nGIUSEPPA TROVATO MAZZA\nFRAZ. LA FONTAINE - 11020 GRESSAN\nTOYOTA YARIS YARIS 1.5H ECVT 5P\nSTYLE MY17\n+39 335 767 0230\nTARGA\nFH 866 KP\nKM\n93.735\nDETTAGLIO INTERVENTI\nIMPORTO\n1 TAGLIANDO AMICO START\n310,99 \u20ac\nTOTALE NETTO\nIVA\n310,99 \u20ac\n68,42 \u20ac\nTOTALE SERVICE\nIVA INCLUSA\n379,41 \u20ac\nSCONTO\nIVA INCLUSA\n44,91 \u20ac\nTOTALE A PAGARE\nIVA INCLUSA\n334,50\nL'AUTOCENTER\nLocalita Grand Chemin 207 - 11020 Saint Christophe\nTelefono 0165235007 - Fax \nOrdine di lavoro\nTCU-23 001-019   09/03/2023\nPAG. 1/2\n COPIA CLIENTE \nORDINE DI LAVORO: TCU-23 001-019 del 09/03/2023\n",
        "output": "{\"id\": \"TCU-23 001-019\", \"total_amount\": 334.5, \"date\": \"2024-03-09\", \"dealer\": {\"name\": \"L'Autocenter\", \"address\": \"Localita Grand Chemin 207 - 11020 Saint Christophe\"}, \"customer\": {\"name\": \"Giuseppa Trovato Mazz\\u00e0\", \"address\": \"Fraz. La Fontaine - 11020 Gressan\", \"email\": null, \"phone_number\": \"+39 335 767 0230\"}, \"car\": {\"model\": \"Toyota Yaris Yaris 1.5H ECVT 5P Style MY17\", \"plate\": \"FH 866 KP\"}}",
        "instruction": "You are a data extraction assistant. Your task is to extract data from the input text and output only a JSON object that strictly follows the schema below:\n\n{\n  \"id\": \"str\",\n  \"total_amount\": \"float\",\n  \"date\": \"str (YYYY-MM-DD)\",\n  \"dealer\": {\n    \"name\": \"str\",\n    \"address\": \"str\"\n  },\n  \"customer\": {\n    \"name\": \"str\",\n    \"address\": \"str\",\n    \"email\": \"str | null\",\n    \"phone_number\": \"str | null\"\n  },\n  \"car\": {\n    \"model\": \"str\",\n    \"plate\": \"str | null\"\n  }\n}\n\nExtraction Rules:\n1. **id**: Extract the value starting with \"TCU\" or \"LCU\" immediately following \"Ordine di lavoro.\" \n2. **total_amount**: Extract the final amount after \"TOTALE COMPLESSIVO IVA INCLUSA.\" \n3. **date**: Extract the date in DD.MM.YYYY format and convert it to YYYY-MM-DD. \n4. **dealer**: Extract the name and address found near \"Telefono\" or \"e-mail.\" \n5. **customer**: Extract the name, address, email, and phone number. If email or phone number is missing, use null. \n6. **car**:\n   - **model**: Extract all lines describing the car starting with the car brand (e.g., \"TOYOTA\").\n   - **plate**: Extract the value found directly below \"TARGA.\"\n\nReturn only a valid JSON object that matches this schema exactly. For any field that is missing or unclear, use null."
    },
    {
        "input": "CONTROLLI ESCLUSIVI TOYOTA\nSCADENZE\nDurante la manutenzione del suo veicolo, il nostro personale spezializzato e\nqualificato proceder\u00e0 con una diagnosi approfondita effettuando i seguenti\ncontrolli:\nSicurezza:\nSistema Impianto frenante e freno a\nmano\n\u2022\nAirbag & Cinture di sicurezza\n\u2022\nLuci & Indicatori di direzione\n\u2022\nPressione Pneumatici\n\u2022\nSospensioni & sterzo\n\u2022\nImpianto carburante\n\u2022\nFunzionalit\u00e0:\nFiltro carburante*\n\u2022\nCandele*\n\u2022\nCinghia ausiliari\n\u2022\nSistema Impianto di scarico\n\u2022\nTrasmissione e giunti\n\u2022\nComfort:\nImpianto A/C\n\u2022\nSpazzole tergi Rabbocco liquido lavavetri\n\u2022\nIntrattenimento di bordo\n\u2022\n* se previsto dal piano di manutenzione\nPROSSIMA\n14/02/2024\nMANUTENZIONE\no 57643Km\nFORTUNATA PIZZIMENTI\nCONTRADA LIVARI SUPERIORE - 89134 REGGIO CALABRIA\nTOYOTA C-HR C-HR 1.8H TREND\nMY19\nnuccio.quattrone@gmail.com\n+39 328 881 0466\nTARGA\nFT 538 WT\nKM\n42.643\nDETTAGLIO INTERVENTI\nIMPORTO\n1 TAGLIANDO 3 - 45.000 KM - DAT:\u00b007/2018+ HYBRID CHECK\n244,49 \u20ac\n2 SOSTITUZIONE TAPPETINO FISSAGGIO/USURA POSIZIONE\n0,45 \u20ac\n3 CONTROLLO STATO PASTICCHE POSTERIORE\n0,45 \u20ac\n4 CONTROLLO STATO PASTICCHE ANTERIORE\n0,45 \u20ac\n5 VETTURA NON SI AVVIA\n18,00 \u20ac\nCONTINUA >\nTOTALE A PAGARE\nIVA INCLUSA\n262,23\nVADALA'\nSuperstrada Ionica, 119 - 89134 Pellaro\nTelefono 0965359958 - Fax 0965359941\nhttp://vadala-toyota.it\nOrdine di lavoro\nTCU-23 001-489   14/02/2023\nPAG. 1/4\n COPIA CLIENTE \nORDINE DI LAVORO: TCU-23 001-489 del 14/02/2023\n",
        "output": "{\"id\": \"TCU-23 001-489\", \"total_amount\": 262.23, \"date\": \"2024-02-14\", \"dealer\": {\"name\": \"VADALA'\", \"address\": \"Superstrada Ionica, 119 - 89134 Pellaro\"}, \"customer\": {\"name\": \"FORTUNATA PIZZIMENTI\", \"address\": \"CONTRADA LIVARI SUPERIORE - 89134 REGGIO CALABRIA\", \"email\": \"nuccio.quattrone@gmail.com\", \"phone_number\": \"+39 328 881 0466\"}, \"car\": {\"model\": \"TOYOTA C-HR C-HR 1.8H TREND MY19\", \"plate\": \"FT 538 WT\"}}",
        "instruction": "You are a data extraction assistant. Your task is to extract data from the input text and output only a JSON object that strictly follows the schema below:\n\n{\n  \"id\": \"str\",\n  \"total_amount\": \"float\",\n  \"date\": \"str (YYYY-MM-DD)\",\n  \"dealer\": {\n    \"name\": \"str\",\n    \"address\": \"str\"\n  },\n  \"customer\": {\n    \"name\": \"str\",\n    \"address\": \"str\",\n    \"email\": \"str | null\",\n    \"phone_number\": \"str | null\"\n  },\n  \"car\": {\n    \"model\": \"str\",\n    \"plate\": \"str | null\"\n  }\n}\n\nExtraction Rules:\n1. **id**: Extract the value starting with \"TCU\" or \"LCU\" immediately following \"Ordine di lavoro.\" \n2. **total_amount**: Extract the final amount after \"TOTALE COMPLESSIVO IVA INCLUSA.\" \n3. **date**: Extract the date in DD.MM.YYYY format and convert it to YYYY-MM-DD. \n4. **dealer**: Extract the name and address found near \"Telefono\" or \"e-mail.\" \n5. **customer**: Extract the name, address, email, and phone number. If email or phone number is missing, use null. \n6. **car**:\n   - **model**: Extract all lines describing the car starting with the car brand (e.g., \"TOYOTA\").\n   - **plate**: Extract the value found directly below \"TARGA.\"\n\nReturn only a valid JSON object that matches this schema exactly. For any field that is missing or unclear, use null."
    },
    {
        "input": "CONTROLLI ESCLUSIVI TOYOTA\nSCADENZE\nDurante la manutenzione del suo veicolo, il nostro personale spezializzato e\nqualificato proceder\u00e0 con una diagnosi approfondita effettuando i seguenti\ncontrolli:\nSicurezza:\nSistema Impianto frenante e freno a\nmano\n\u2022\nAirbag & Cinture di sicurezza\n\u2022\nLuci & Indicatori di direzione\n\u2022\nPressione Pneumatici\n\u2022\nSospensioni & sterzo\n\u2022\nImpianto carburante\n\u2022\nFunzionalit\u00e0:\nFiltro carburante*\n\u2022\nCandele*\n\u2022\nCinghia ausiliari\n\u2022\nSistema Impianto di scarico\n\u2022\nTrasmissione e giunti\n\u2022\nComfort:\nImpianto A/C\n\u2022\nSpazzole tergi Rabbocco liquido lavavetri\n\u2022\nIntrattenimento di bordo\n\u2022\n* se previsto dal piano di manutenzione\nPROSSIMA\n30/12/2023\nMANUTENZIONE\no 30144Km\nMARIANNA TROTTA\nVIA E.P. DE FONSECA - 85046 MARATEA\nTOYOTA YARIS YARIS HYBRID 1.5H\nACTIVE\nMARIANNATROTTA@TISCALI.IT\n+39 338 433 2672\nTARGA\nGH 535 PE\nKM\n15.144\nDETTAGLIO INTERVENTI\nIMPORTO\n1 ANNO 1 - 15,000 KM - SEVERO - OPERAZIONE BASE\n218,57 \u20ac\nTOTALE NETTO\nIVA\n218,57 \u20ac\n48,09 \u20ac\nTOTALE SERVICE\nIVA INCLUSA\n266,66 \u20ac\nSCONTO\nIVA INCLUSA\n23,92 \u20ac\nTOTALE A PAGARE\nIVA INCLUSA\n242,74\nCENTER\nVia delle Calabrie, 22 - 84131 Salerno\nTelefono 0893061501 - Fax 0893061520\nhttp://center-toyota.it\nOrdine di lavoro\nTCU-22 007-351   30/12/2022\nPAG. 1/2\n COPIA CLIENTE \nORDINE DI LAVORO: TCU-22 007-351 del 30/12/2022\n",
        "output": "{\"id\": \"TCU-22 007-351\", \"total_amount\": 242.74, \"date\": \"2023-12-30\", \"dealer\": {\"name\": \"CENTER\", \"address\": \"Via delle Calabrie, 22 - 84131 Salerno\"}, \"customer\": {\"name\": \"MARIANNA TROTTA\", \"address\": \"VIA E.P. DE FONSECA - 85046 MARATEA\", \"email\": \"mariannatrottatiscali.it\", \"phone_number\": \"+39 338 433 2672\"}, \"car\": {\"model\": \"TOYOTA YARIS YARIS HYBRID 1.5H ACTIVE\", \"plate\": \"GH 535 PE\"}}",
        "instruction": "You are a data extraction assistant. Your task is to extract data from the input text and output only a JSON object that strictly follows the schema below:\n\n{\n  \"id\": \"str\",\n  \"total_amount\": \"float\",\n  \"date\": \"str (YYYY-MM-DD)\",\n  \"dealer\": {\n    \"name\": \"str\",\n    \"address\": \"str\"\n  },\n  \"customer\": {\n    \"name\": \"str\",\n    \"address\": \"str\",\n    \"email\": \"str | null\",\n    \"phone_number\": \"str | null\"\n  },\n  \"car\": {\n    \"model\": \"str\",\n    \"plate\": \"str | null\"\n  }\n}\n\nExtraction Rules:\n1. **id**: Extract the value starting with \"TCU\" or \"LCU\" immediately following \"Ordine di lavoro.\" \n2. **total_amount**: Extract the final amount after \"TOTALE COMPLESSIVO IVA INCLUSA.\" \n3. **date**: Extract the date in DD.MM.YYYY format and convert it to YYYY-MM-DD. \n4. **dealer**: Extract the name and address found near \"Telefono\" or \"e-mail.\" \n5. **customer**: Extract the name, address, email, and phone number. If email or phone number is missing, use null. \n6. **car**:\n   - **model**: Extract all lines describing the car starting with the car brand (e.g., \"TOYOTA\").\n   - **plate**: Extract the value found directly below \"TARGA.\"\n\nReturn only a valid JSON object that matches this schema exactly. For any field that is missing or unclear, use null."
    },
    {
        "input": "CONTROLLI ESCLUSIVI TOYOTA\nSCADENZE\nDurante la manutenzione del suo veicolo, il nostro personale spezializzato e\nqualificato proceder\u00e0 con una diagnosi approfondita effettuando i seguenti\ncontrolli:\nSicurezza:\nSistema Impianto frenante e freno a\nmano\n\u2022\nAirbag & Cinture di sicurezza\n\u2022\nLuci & Indicatori di direzione\n\u2022\nPressione Pneumatici\n\u2022\nSospensioni & sterzo\n\u2022\nImpianto carburante\n\u2022\nFunzionalit\u00e0:\nFiltro carburante*\n\u2022\nCandele*\n\u2022\nCinghia ausiliari\n\u2022\nSistema Impianto di scarico\n\u2022\nTrasmissione e giunti\n\u2022\nComfort:\nImpianto A/C\n\u2022\nSpazzole tergi Rabbocco liquido lavavetri\n\u2022\nIntrattenimento di bordo\n\u2022\n* se previsto dal piano di manutenzione\nPROSSIMA\n10/02/2024\nMANUTENZIONE\no 257157Km\nDamiano Felice Varacalli\nVia Pellegrina 1 - 89048 Siderno\nTOYOTA RAV4 RAV4 2.0D M ACTIVE\n2WD MY14+\ndamianovaracalli@libero.it\n+39 328 474 3406\nTARGA\nEW 299 ZE\nKM\n242.157\nDETTAGLIO INTERVENTI\nIMPORTO\n1 SOSTITUIRE IL FILTRO DELL'ARIA E IL FILTRO ANTIPOLLINE IN CABINA - OPERAZIONE BASE\n69,68 \u20ac\n2 TAGLIANDO AMICO START - TAGLIANDO AMICO START\n236,08 \u20ac\nTOTALE NETTO\nIVA\n305,76 \u20ac\n67,27 \u20ac\nTOTALE SERVICE\nIVA INCLUSA\n373,03 \u20ac\nSCONTO\nIVA INCLUSA\n102,37 \u20ac\nTOTALE A PAGARE\nIVA INCLUSA\n270,66\nVADALA'\nC.Da Misserianni SS 106 L.Nord - 89040 Siderno\nTelefono 0964347724 - Fax 0964347781\nhttp://vadala-toyota.it\nOrdine di lavoro\nTCU-23 001-553   10/02/2023\nPAG. 1/3\n COPIA CLIENTE \nORDINE DI LAVORO: TCU-23 001-553 del 10/02/2023\n",
        "output": "{\"id\": \"TCU-23 001-553\", \"total_amount\": 270.66, \"date\": \"2024-02-10\", \"dealer\": {\"name\": \"Vadala'\", \"address\": \"C.Da Misserianni SS 106 L.Nord - 89040 Siderno\"}, \"customer\": {\"name\": \"Damiano Felice Varacalli\", \"address\": \"Via Pellegrina 1 - 89048 Siderno\", \"email\": \"damianovaracalli@libero.it\", \"phone_number\": \"+39 328 474 3406\"}, \"car\": {\"model\": \"TOYOTA RAV4 RAV4 2.0D M ACTIVE 2WD MY14+\", \"plate\": \"EW 299 ZE\"}}",
        "instruction": "You are a data extraction assistant. Your task is to extract data from the input text and output only a JSON object that strictly follows the schema below:\n\n{\n  \"id\": \"str\",\n  \"total_amount\": \"float\",\n  \"date\": \"str (YYYY-MM-DD)\",\n  \"dealer\": {\n    \"name\": \"str\",\n    \"address\": \"str\"\n  },\n  \"customer\": {\n    \"name\": \"str\",\n    \"address\": \"str\",\n    \"email\": \"str | null\",\n    \"phone_number\": \"str | null\"\n  },\n  \"car\": {\n    \"model\": \"str\",\n    \"plate\": \"str | null\"\n  }\n}\n\nExtraction Rules:\n1. **id**: Extract the value starting with \"TCU\" or \"LCU\" immediately following \"Ordine di lavoro.\" \n2. **total_amount**: Extract the final amount after \"TOTALE COMPLESSIVO IVA INCLUSA.\" \n3. **date**: Extract the date in DD.MM.YYYY format and convert it to YYYY-MM-DD. \n4. **dealer**: Extract the name and address found near \"Telefono\" or \"e-mail.\" \n5. **customer**: Extract the name, address, email, and phone number. If email or phone number is missing, use null. \n6. **car**:\n   - **model**: Extract all lines describing the car starting with the car brand (e.g., \"TOYOTA\").\n   - **plate**: Extract the value found directly below \"TARGA.\"\n\nReturn only a valid JSON object that matches this schema exactly. For any field that is missing or unclear, use null."
    },
    {
        "input": " KINTO ITALIA SPA\nVIA KIICIRO TOYODA - 00148 ROMA\nTOYOTA HILUX HILUX 2.4D M DC\n4WD CMF MY21\nkintoitalia@legalmail.it\n+39 06 602301\nTARGA\nGD 213 TN\nKM\n79.397\nDETTAGLIO INTERVENTI\nIMPORTO\n1 IL CLIENTE SEGNALA DI ESSERE RIMASTO IN PANNE , NESSUN ACCOPPIAMENTO AVVIENE\nINSERENDO QUALSIASI MARCIA\n23,00 \u20ac\nTOTALE NETTO\nIVA\n23,00 \u20ac\n5,06 \u20ac\nTOTALE A PAGARE\nIVA INCLUSA\n28,06\nPASQUARELLI AUTO\nC.Da Colle Api V.Giovannitti - 86100 Campabasso\nTelefono 08741863050 - Fax 0874493778\nOrdine di lavoro\nTCU-22 008-135   19/12/2022\nPAG. 1/2\n COPIA CLIENTE \nORDINE DI LAVORO: TCU-22 008-135 del 19/12/2022\n",
        "output": "{\"id\": \"TCU-22 008-135\", \"total_amount\": 28.06, \"date\": \"2022-12-19\", \"dealer\": {\"name\": \"PASQUARELLI AUTO\", \"address\": \"C.Da Colle Api V.Giovannitti - 86100 Campabasso\"}, \"customer\": {\"name\": \"\", \"address\": \"\", \"email\": \"kintoitalia@legalmail.it\", \"phone_number\": \"+39 06 602301\"}, \"car\": {\"model\": \"TOYOTA HILUX HILUX 2.4D M DC 4WD CMF MY21\", \"plate\": \"GD 213 TN\"}}",
        "instruction": "You are a data extraction assistant. Your task is to extract data from the input text and output only a JSON object that strictly follows the schema below:\n\n{\n  \"id\": \"str\",\n  \"total_amount\": \"float\",\n  \"date\": \"str (YYYY-MM-DD)\",\n  \"dealer\": {\n    \"name\": \"str\",\n    \"address\": \"str\"\n  },\n  \"customer\": {\n    \"name\": \"str\",\n    \"address\": \"str\",\n    \"email\": \"str | null\",\n    \"phone_number\": \"str | null\"\n  },\n  \"car\": {\n    \"model\": \"str\",\n    \"plate\": \"str | null\"\n  }\n}\n\nExtraction Rules:\n1. **id**: Extract the value starting with \"TCU\" or \"LCU\" immediately following \"Ordine di lavoro.\" \n2. **total_amount**: Extract the final amount after \"TOTALE COMPLESSIVO IVA INCLUSA.\" \n3. **date**: Extract the date in DD.MM.YYYY format and convert it to YYYY-MM-DD. \n4. **dealer**: Extract the name and address found near \"Telefono\" or \"e-mail.\" \n5. **customer**: Extract the name, address, email, and phone number. If email or phone number is missing, use null. \n6. **car**:\n   - **model**: Extract all lines describing the car starting with the car brand (e.g., \"TOYOTA\").\n   - **plate**: Extract the value found directly below \"TARGA.\"\n\nReturn only a valid JSON object that matches this schema exactly. For any field that is missing or unclear, use null."
    }
]